{
 "base": {
  "repo": {
   "name": "paper-qa-feedstock"
  }
 },
 "closed_at": null,
 "created_at": "2025-02-22T06:07:05Z",
 "draft": false,
 "e_tag": "\"709aa825d628cc3c08c5d9645320b7704e4ce82170278d804fa2fa0d7a2e6f5d\"",
 "head": {
  "ref": "5.14.0_hcd051d"
 },
 "html_url": "https://github.com/conda-forge/paper-qa-feedstock/pull/39",
 "id": 2350987496,
 "labels": [],
 "last_modified": null,
 "mergeable": null,
 "mergeable_state": "unknown",
 "merged": false,
 "merged_at": null,
 "number": 39,
 "state": "open",
 "updated_at": "2025-02-22T06:07:05Z"
}