{
 "base": {
  "repo": {
   "name": "arize-phoenix-feedstock"
  }
 },
 "closed_at": null,
 "created_at": "2025-02-13T07:04:59Z",
 "draft": false,
 "e_tag": "\"839b68adbee90752d149be0bf6124540449fad72c57f723e0b0abadd55b2c584\"",
 "head": {
  "ref": "7.12.1_he6b7c5"
 },
 "html_url": "https://github.com/conda-forge/arize-phoenix-feedstock/pull/204",
 "id": 2333008830,
 "labels": [],
 "last_modified": null,
 "mergeable": null,
 "mergeable_state": "unknown",
 "merged": false,
 "merged_at": null,
 "number": 204,
 "state": "open",
 "updated_at": "2025-02-13T07:04:59Z"
}