{
 "base": {
  "repo": {
   "name": "r-faraway-feedstock"
  }
 },
 "closed_at": null,
 "created_at": "2025-02-07T18:13:01Z",
 "draft": false,
 "e_tag": "\"a2987f136aa5c50867877d680d1d9a49c91d73138bc3619559916ff8332c38c6\"",
 "head": {
  "ref": "1.0.9_h18a3f7"
 },
 "html_url": "https://github.com/conda-forge/r-faraway-feedstock/pull/5",
 "id": 2322851710,
 "labels": [],
 "last_modified": null,
 "mergeable": null,
 "mergeable_state": "unknown",
 "merged": false,
 "merged_at": null,
 "number": 5,
 "state": "open",
 "updated_at": "2025-02-07T18:13:01Z"
}