{
 "base": {
  "repo": {
   "name": "clad-feedstock"
  }
 },
 "closed_at": null,
 "created_at": "2025-02-10T22:09:22Z",
 "draft": false,
 "e_tag": "\"ad5b5cfaf6bfc062c470e00308ea66252ceb8fa5453fc8b0eed162ff66c5b90d\"",
 "head": {
  "ref": "1.9_h0a39ab"
 },
 "html_url": "https://github.com/conda-forge/clad-feedstock/pull/29",
 "id": 2327317745,
 "labels": [],
 "last_modified": null,
 "mergeable": null,
 "mergeable_state": "unknown",
 "merged": false,
 "merged_at": null,
 "number": 29,
 "state": "open",
 "updated_at": "2025-02-10T22:09:22Z"
}