{
 "ETag": "W/\"52f52ede773e8732d87425d6664da83b537219d22f24388d06f4068fbc53defc\"",
 "Last-Modified": "Fri, 21 Feb 2025 20:16:50 GMT",
 "base": {
  "repo": {
   "name": "pytensor-suite-feedstock"
  }
 },
 "closed_at": null,
 "created_at": "2025-02-21T20:07:59Z",
 "draft": false,
 "e_tag": "\"bc6d681c9d6ac50fe213fed868dc99d8bd6b00c95e6a571e53e17ba7545cceec\"",
 "head": {
  "ref": "rebuild-numpy2-0-1_h21cdf7"
 },
 "html_url": "https://github.com/conda-forge/pytensor-suite-feedstock/pull/136",
 "id": 2350435329,
 "labels": [
  {
   "color": "0e8a16",
   "default": false,
   "description": "Merge the PR when CI passes",
   "id": 4837761745,
   "name": "automerge",
   "node_id": "LA_kwDOIf2fIc8AAAABIFpi0Q",
   "url": "https://api.github.com/repos/conda-forge/pytensor-suite-feedstock/labels/automerge"
  }
 ],
 "last_modified": null,
 "mergeable": true,
 "mergeable_state": "unstable",
 "merged": false,
 "merged_at": null,
 "number": 136,
 "state": "open",
 "updated_at": "2025-02-21T20:16:50Z"
}