{
 "base": {
  "repo": {
   "name": "cvat-cli-feedstock"
  }
 },
 "closed_at": null,
 "created_at": "2025-01-29T22:41:50Z",
 "draft": false,
 "e_tag": "\"b5ff4179e4827bf49479bf68f48ce1f11dead27e610f0e8aa48f841d4fcbfeca\"",
 "head": {
  "ref": "2.26.1_hd29811"
 },
 "html_url": "https://github.com/conda-forge/cvat-cli-feedstock/pull/3",
 "id": 2305693763,
 "labels": [],
 "last_modified": null,
 "mergeable": null,
 "mergeable_state": "unknown",
 "merged": false,
 "merged_at": null,
 "number": 3,
 "state": "open",
 "updated_at": "2025-01-29T22:41:50Z"
}