{
 "base": {
  "repo": {
   "name": "popsregression-feedstock"
  }
 },
 "closed_at": null,
 "created_at": "2025-02-05T15:42:08Z",
 "draft": false,
 "e_tag": "\"8325417161d21fa696d01c883206ee5723c4761e5484d4ad915354223c9df761\"",
 "head": {
  "ref": "0.3.0_h5f3389"
 },
 "html_url": "https://github.com/conda-forge/popsregression-feedstock/pull/5",
 "id": 2317940230,
 "labels": [],
 "last_modified": null,
 "mergeable": null,
 "mergeable_state": "unknown",
 "merged": false,
 "merged_at": null,
 "number": 5,
 "state": "open",
 "updated_at": "2025-02-05T15:42:08Z"
}