{
 "base": {
  "repo": {
   "name": "opentelemetry-instrumentation-pyramid-feedstock"
  }
 },
 "closed_at": null,
 "created_at": "2025-02-07T05:28:53Z",
 "draft": false,
 "e_tag": "\"f8a65ca8c48d001aaf1bac6fbf5ef5975a13b8488432efafc1c84da58ca8fafa\"",
 "head": {
  "ref": "0.51b0_hf9dc7a"
 },
 "html_url": "https://github.com/conda-forge/opentelemetry-instrumentation-pyramid-feedstock/pull/32",
 "id": 2321495227,
 "labels": [],
 "last_modified": null,
 "mergeable": null,
 "mergeable_state": "unknown",
 "merged": false,
 "merged_at": null,
 "number": 32,
 "state": "open",
 "updated_at": "2025-02-07T05:28:53Z"
}