{
 "PRed": [
  {
   "PR": {
    "__lazy_json__": "pr_json/1414296206.json"
   },
   "data": {
    "bot_rerun": false,
    "migrator_name": "Version",
    "migrator_version": 0,
    "version": "0.13.0"
   },
   "keys": [
    "bot_rerun",
    "migrator_name",
    "migrator_version",
    "version"
   ]
  },
  {
   "PR": {
    "labels": [
     {
      "name": "bot-rerun"
     }
    ],
    "number": 2,
    "state": "closed"
   },
   "data": {
    "bot_rerun": 1697498989.2772012,
    "migrator_name": "Version",
    "migrator_version": 0,
    "version": "0.13.1"
   },
   "keys": [
    "bot_rerun",
    "migrator_name",
    "migrator_version",
    "version"
   ]
  },
  {
   "PR": {
    "__lazy_json__": "pr_json/1559639641.json"
   },
   "data": {
    "bot_rerun": false,
    "migrator_name": "Version",
    "migrator_version": 0,
    "version": "0.13.1"
   },
   "keys": [
    "bot_rerun",
    "migrator_name",
    "migrator_version",
    "version"
   ]
  },
  {
   "PR": {
    "__lazy_json__": "pr_json/2215980625.json"
   },
   "data": {
    "bot_rerun": false,
    "migrator_name": "Replacement",
    "migrator_version": 0,
    "name": "astropy-to-astropy-base"
   },
   "keys": [
    "bot_rerun",
    "migrator_name",
    "migrator_version",
    "name"
   ]
  }
 ],
 "bad": false,
 "pinning_version": "2024.12.04.17.04.39",
 "pre_pr_migrator_attempts": {
  "noarch_python_min": 5
 },
 "pre_pr_migrator_status": {
  "noarch_python_min": "not solvable (<a href='https://github.com/regro/cf-scripts/actions/runs/12909384475'>bot CI job</a>) @ main\n        <details>\n        <div align=\"left\">\n        <pre>\n        linux_64_: Cannot solve the request because of: coverage 4.5.4.* cannot be installed because there are no viable options:\n\u2514\u2500 coverage 4.5.4 | 4.5.4 | 4.5.4 | 4.5.4 would require\n   \u2514\u2500 python >=2.7,<2.8.0a0, for which no candidates were found.\n\n        </pre>\n        </div>\n        </details>"
 },
 "smithy_version": "3.44.9"
}