{
 "base": {
  "repo": {
   "name": "tox-uv-feedstock"
  }
 },
 "closed_at": null,
 "created_at": "2025-02-08T04:29:00Z",
 "draft": false,
 "e_tag": "\"056eedcf0bd3da6f19c08465367e301f2c3da4a8b0e495d4c71435f56a6bbe03\"",
 "head": {
  "ref": "1.23.0_h7c8191"
 },
 "html_url": "https://github.com/conda-forge/tox-uv-feedstock/pull/13",
 "id": 2323508419,
 "labels": [],
 "last_modified": null,
 "mergeable": null,
 "mergeable_state": "unknown",
 "merged": false,
 "merged_at": null,
 "number": 13,
 "state": "open",
 "updated_at": "2025-02-08T04:29:00Z"
}