{
 "ETag": "W/\"9816b1afb68646fccc0ba6a954ef0ca0d9a94f3848b19816fb4389d6f8f58461\"",
 "Last-Modified": "Tue, 11 Feb 2025 02:56:25 GMT",
 "base": {
  "repo": {
   "name": "soxs-feedstock"
  }
 },
 "closed_at": null,
 "created_at": "2025-02-11T02:55:04Z",
 "draft": false,
 "e_tag": "\"f0928ae21d644256511d6a684b748a1b0a610bda6cfff2260e90a93b27cbd5b0\"",
 "head": {
  "ref": "astropy-to-astropy-base-migration-0_h6eb192"
 },
 "html_url": "https://github.com/conda-forge/soxs-feedstock/pull/29",
 "id": 2327626252,
 "labels": [],
 "last_modified": null,
 "mergeable": true,
 "mergeable_state": "unstable",
 "merged": false,
 "merged_at": null,
 "number": 29,
 "state": "open",
 "updated_at": "2025-02-11T02:56:25Z"
}