{
 "base": {
  "repo": {
   "name": "tox-uv-feedstock"
  }
 },
 "closed_at": null,
 "created_at": "2025-02-15T08:10:49Z",
 "draft": false,
 "e_tag": "\"438c04410a0102222977e746a76da01df3e3195b30f83b0bc69bc19a79d8bde4\"",
 "head": {
  "ref": "1.23.2_h621cb0"
 },
 "html_url": "https://github.com/conda-forge/tox-uv-feedstock/pull/15",
 "id": 2337606509,
 "labels": [],
 "last_modified": null,
 "mergeable": null,
 "mergeable_state": "unknown",
 "merged": false,
 "merged_at": null,
 "number": 15,
 "state": "open",
 "updated_at": "2025-02-15T08:10:49Z"
}