{
 "ETag": "W/\"a5a2134695db23d346558d4d6552938b3826d7f8411ea95d8367748b3cdce82c\"",
 "Last-Modified": "Fri, 24 Jan 2025 22:28:02 GMT",
 "base": {
  "repo": {
   "name": "basemap-feedstock"
  }
 },
 "closed_at": null,
 "created_at": "2025-01-24T22:26:41Z",
 "draft": false,
 "e_tag": "\"4be7661c7b9ae67ac8a4858899f54c7973a54391945d352817c6c205803cc2f0\"",
 "head": {
  "ref": "noarch_python_min-migration-1_h93ea52"
 },
 "html_url": "https://github.com/conda-forge/basemap-feedstock/pull/137",
 "id": 2297717079,
 "labels": [],
 "last_modified": null,
 "mergeable": true,
 "mergeable_state": "unstable",
 "merged": false,
 "merged_at": null,
 "number": 137,
 "state": "open",
 "updated_at": "2025-01-24T22:28:02Z"
}