{
 "ETag": "W/\"fea5ce6d04840f9e642286d10e9ab47b069499b5886c28fafe158976115684ab\"",
 "Last-Modified": "Sat, 08 Feb 2025 00:44:24 GMT",
 "base": {
  "repo": {
   "name": "dbt-adapters-feedstock"
  }
 },
 "closed_at": null,
 "created_at": "2025-02-08T00:42:37Z",
 "draft": false,
 "e_tag": "\"7a543d803ea5e4727963421c17f999a0f99d386549b1ab47933ae1cefeed9a0a\"",
 "head": {
  "ref": "1.14.0_h398744"
 },
 "html_url": "https://github.com/conda-forge/dbt-adapters-feedstock/pull/21",
 "id": 2323364163,
 "labels": [],
 "last_modified": null,
 "mergeable": true,
 "mergeable_state": "unstable",
 "merged": false,
 "merged_at": null,
 "number": 21,
 "state": "open",
 "updated_at": "2025-02-08T00:44:24Z"
}