{
 "base": {
  "repo": {
   "name": "spicetify-cli-feedstock"
  }
 },
 "closed_at": null,
 "created_at": "2025-02-09T10:49:22Z",
 "draft": false,
 "e_tag": "\"5a023493e7611bc68de5eb06ab5b3d31e1a3dd50f629a71ff3586fe8a52aa3b7\"",
 "head": {
  "ref": "2.39.2_h67e97c"
 },
 "html_url": "https://github.com/conda-forge/spicetify-cli-feedstock/pull/9",
 "id": 2324435467,
 "labels": [],
 "last_modified": null,
 "mergeable": null,
 "mergeable_state": "unknown",
 "merged": false,
 "merged_at": null,
 "number": 9,
 "state": "open",
 "updated_at": "2025-02-09T10:49:22Z"
}