{
 "ETag": "W/\"ea1bea5230c134e37275e372b8ad2a6fdea1eae452a754bd5c3136c4d1815e61\"",
 "Last-Modified": "Wed, 29 Jan 2025 21:47:53 GMT",
 "base": {
  "repo": {
   "name": "root-feedstock"
  }
 },
 "closed_at": "2025-01-29T21:47:53Z",
 "created_at": "2024-12-20T14:16:01Z",
 "draft": false,
 "e_tag": "\"5b41643769828a890f2927eb67b8767164a6ea1644bcaf1d54911f101ce6a274\"",
 "head": {
  "ref": "rebuild-lz4_c110-0-1_hf2dd95"
 },
 "html_url": "https://github.com/conda-forge/root-feedstock/pull/276",
 "id": 2246787713,
 "labels": [],
 "last_modified": null,
 "mergeable": null,
 "mergeable_state": "unknown",
 "merged": false,
 "merged_at": null,
 "number": 276,
 "state": "closed",
 "updated_at": "2025-01-29T21:47:53Z"
}