{
 "base": {
  "repo": {
   "name": "pandora-geno-feedstock"
  }
 },
 "closed_at": null,
 "created_at": "2025-01-29T14:26:32Z",
 "draft": false,
 "e_tag": "\"7fe70848883b09b5b7be9e742b4ae31db139cfdbc5b3592b7f996db0d4dfd91f\"",
 "head": {
  "ref": "noarch_python_min-migration-1_hfaba52"
 },
 "html_url": "https://github.com/conda-forge/pandora-geno-feedstock/pull/13",
 "id": 2304697626,
 "labels": [],
 "last_modified": null,
 "mergeable": null,
 "mergeable_state": "unknown",
 "merged": false,
 "merged_at": null,
 "number": 13,
 "state": "open",
 "updated_at": "2025-01-29T14:26:32Z"
}