{
 "base": {
  "repo": {
   "name": "sxs-feedstock"
  }
 },
 "closed_at": null,
 "created_at": "2025-01-31T07:37:25Z",
 "draft": false,
 "e_tag": "\"4c1bbb9bb1004510bd7c32c5768d2d66bd4900f35371918191046ef5cd50462d\"",
 "head": {
  "ref": "2024.0.28_he8a868"
 },
 "html_url": "https://github.com/conda-forge/sxs-feedstock/pull/96",
 "id": 2308483856,
 "labels": [],
 "last_modified": null,
 "mergeable": null,
 "mergeable_state": "unknown",
 "merged": false,
 "merged_at": null,
 "number": 96,
 "state": "open",
 "updated_at": "2025-01-31T07:37:25Z"
}