{
 "ETag": "W/\"60c0211c623009038c81800d145588f29b1635eea58d21be98396f606b1fdb9d\"",
 "Last-Modified": "Sat, 01 Feb 2025 10:04:44 GMT",
 "base": {
  "repo": {
   "name": "dist_s1_enumerator-feedstock"
  }
 },
 "closed_at": null,
 "created_at": "2025-02-01T10:03:23Z",
 "draft": false,
 "e_tag": "\"3af3c04d0a49e592fe4722af0913bf6f727ede704a3d32c641d4fd07c1a8baed\"",
 "head": {
  "ref": "0.0.7_h972e52"
 },
 "html_url": "https://github.com/conda-forge/dist_s1_enumerator-feedstock/pull/5",
 "id": 2310683108,
 "labels": [],
 "last_modified": null,
 "mergeable": true,
 "mergeable_state": "clean",
 "merged": false,
 "merged_at": null,
 "number": 5,
 "state": "open",
 "updated_at": "2025-02-01T10:04:44Z"
}