{
 "ETag": "W/\"42fc2898f92bce44d0153fc254f82a5f8a4d79ccfc483bb00c9e6ed61b6b2102\"",
 "Last-Modified": "Tue, 18 Feb 2025 15:30:22 GMT",
 "base": {
  "repo": {
   "name": "fractal-client-feedstock"
  }
 },
 "closed_at": "2025-02-18T15:30:22Z",
 "created_at": "2025-02-17T12:53:02Z",
 "draft": false,
 "e_tag": "\"3f9aa5c910f0ad33199cec1adccda301db0e590821323c191e5c44221cfcd5dd\"",
 "head": {
  "ref": "this_is_not_a_branch"
 },
 "html_url": "https://github.com/conda-forge/fractal-client-feedstock/pull/23",
 "id": 2339683056,
 "labels": [],
 "last_modified": null,
 "mergeable": null,
 "mergeable_state": "unknown",
 "merged": true,
 "merged_at": "2025-02-18T15:30:22Z",
 "number": 23,
 "state": "closed",
 "updated_at": "2025-02-18T15:30:22Z"
}