{
 "ETag": "W/\"0a572ede8e472179dee7976129df0044828b4d5f0ca2205e865996c31b510ff6\"",
 "Last-Modified": "Sun, 16 Feb 2025 20:43:39 GMT",
 "base": {
  "repo": {
   "name": "unstructured-client-feedstock"
  }
 },
 "closed_at": "2025-02-16T20:43:36Z",
 "created_at": "2025-02-16T20:37:17Z",
 "draft": false,
 "e_tag": "\"d43e6b5d75a378158e913bd100aa2d1ed3c36bf4c74f5b5c204091f6f09aacb1\"",
 "head": {
  "ref": "this_is_not_a_branch"
 },
 "html_url": "https://github.com/conda-forge/unstructured-client-feedstock/pull/35",
 "id": 2338401282,
 "labels": [],
 "last_modified": null,
 "mergeable": null,
 "mergeable_state": "unknown",
 "merged": true,
 "merged_at": "2025-02-16T20:43:36Z",
 "number": 35,
 "state": "closed",
 "updated_at": "2025-02-16T20:43:39Z"
}