{
 "base": {
  "repo": {
   "name": "microsoft-kiota-abstractions-feedstock"
  }
 },
 "closed_at": null,
 "created_at": "2025-01-29T20:39:47Z",
 "draft": false,
 "e_tag": "\"72f4672d0610f6fa3786bedb9a94f7ca457783417208a13a29c97bd05344c66f\"",
 "head": {
  "ref": "1.9.1_he5c34f"
 },
 "html_url": "https://github.com/conda-forge/microsoft-kiota-abstractions-feedstock/pull/21",
 "id": 2305481438,
 "labels": [],
 "last_modified": null,
 "mergeable": null,
 "mergeable_state": "unknown",
 "merged": false,
 "merged_at": null,
 "number": 21,
 "state": "open",
 "updated_at": "2025-01-29T20:39:47Z"
}