{
 "ETag": "W/\"43f191494e2090d2f0bf78fda4b5e2c86b2cb85207b414882370973b9d7c5023\"",
 "Last-Modified": "Mon, 10 Feb 2025 07:27:09 GMT",
 "base": {
  "repo": {
   "name": "cwcwidth-feedstock"
  }
 },
 "closed_at": "2025-02-10T07:27:05Z",
 "created_at": "2025-02-10T07:12:43Z",
 "draft": false,
 "e_tag": "\"5e4db068dbb1825d5c359cdcf9a0c7ad72e392962f25502b48d84e9f0aad88c5\"",
 "head": {
  "ref": "this_is_not_a_branch"
 },
 "html_url": "https://github.com/conda-forge/cwcwidth-feedstock/pull/17",
 "id": 2325274291,
 "labels": [],
 "last_modified": null,
 "mergeable": null,
 "mergeable_state": "unknown",
 "merged": true,
 "merged_at": "2025-02-10T07:27:05Z",
 "number": 17,
 "state": "closed",
 "updated_at": "2025-02-10T07:27:09Z"
}