{
 "ETag": "W/\"6abe91d75dd808eb75bd7b96ae445141754f29fcb5eaab52d1a3f23348f9a582\"",
 "Last-Modified": "Thu, 30 Jan 2025 23:34:13 GMT",
 "base": {
  "repo": {
   "name": "r-torch-feedstock"
  }
 },
 "closed_at": null,
 "created_at": "2025-01-30T23:25:38Z",
 "draft": false,
 "e_tag": "\"2f63f4733b0455742b77a461c9f8cb417165e06750c6b0bab34ab5d450ea542f\"",
 "head": {
  "ref": "0.14.0_h58056d"
 },
 "html_url": "https://github.com/conda-forge/r-torch-feedstock/pull/8",
 "id": 2307941860,
 "labels": [],
 "last_modified": null,
 "mergeable": true,
 "mergeable_state": "unstable",
 "merged": false,
 "merged_at": null,
 "number": 8,
 "state": "open",
 "updated_at": "2025-01-30T23:34:13Z"
}