{
 "ETag": "W/\"d7ec91c645437c6da599f91ec81501c3e5e4526e802f27ebbbf323f48c6846da\"",
 "Last-Modified": "Fri, 31 Jan 2025 16:25:21 GMT",
 "base": {
  "repo": {
   "name": "pyformlang-feedstock"
  }
 },
 "closed_at": "2025-01-31T16:25:20Z",
 "created_at": "2024-03-18T21:57:56Z",
 "draft": false,
 "head": {
  "ref": "1.0.9_hc0dc24"
 },
 "html_url": "https://github.com/conda-forge/pyformlang-feedstock/pull/6",
 "id": 1778520268,
 "labels": [],
 "mergeable": false,
 "mergeable_state": "dirty",
 "merged": false,
 "merged_at": null,
 "number": 6,
 "state": "closed",
 "updated_at": "2025-01-31T16:25:21Z"
}