{
 "ETag": "W/\"6556df8a1261f7c328cc35294cd19dcceeb960a0b77a488f3a9cb8e2e67268f3\"",
 "Last-Modified": "Wed, 12 Feb 2025 19:40:20 GMT",
 "base": {
  "repo": {
   "name": "batchgeneratorsv2-feedstock"
  }
 },
 "closed_at": "2025-02-12T19:40:15Z",
 "created_at": "2025-02-12T19:33:40Z",
 "draft": false,
 "e_tag": "\"ac4722bf6bc3a6ee97a884fe158fb2db0c55644464eeecc872c4347d0556c6c6\"",
 "head": {
  "ref": "this_is_not_a_branch"
 },
 "html_url": "https://github.com/conda-forge/batchgeneratorsv2-feedstock/pull/4",
 "id": 2332146856,
 "labels": [],
 "last_modified": null,
 "mergeable": null,
 "mergeable_state": "unknown",
 "merged": true,
 "merged_at": "2025-02-12T19:40:15Z",
 "number": 4,
 "state": "closed",
 "updated_at": "2025-02-12T19:40:20Z"
}