{
 "ETag": "W/\"9cde1f115ac36938bd2a9e61213d17a14ff61e0f4f41f3b0292665c11930c1a5\"",
 "Last-Modified": "Mon, 10 Feb 2025 19:51:45 GMT",
 "base": {
  "repo": {
   "name": "qdoas-feedstock"
  }
 },
 "closed_at": "2025-02-10T19:51:45Z",
 "created_at": "2025-02-10T16:49:00Z",
 "draft": false,
 "e_tag": "\"ecd21d3151dd3c7a7e34581317a95744e28844462097208001fef47ee9c84a29\"",
 "head": {
  "ref": "3.7.2_hb02dd9"
 },
 "html_url": "https://github.com/conda-forge/qdoas-feedstock/pull/18",
 "id": 2326619758,
 "labels": [],
 "last_modified": null,
 "mergeable": true,
 "mergeable_state": "clean",
 "merged": false,
 "merged_at": null,
 "number": 18,
 "state": "closed",
 "updated_at": "2025-02-10T19:51:45Z"
}