{
 "ETag": "W/\"ca14504b9d3bd70cccb2b653413e09d007c4ca9d48060c1ca70c1fcf9de34353\"",
 "Last-Modified": "Fri, 31 Jan 2025 00:42:01 GMT",
 "base": {
  "repo": {
   "name": "boost-histogram-feedstock"
  }
 },
 "closed_at": "2025-01-31T00:41:58Z",
 "created_at": "2025-01-31T00:21:50Z",
 "draft": false,
 "e_tag": "\"86883a562c58b82de06979c3dc28c8f8112b529be767d1c38d5140f6dfdcc5e6\"",
 "head": {
  "ref": "this_is_not_a_branch"
 },
 "html_url": "https://github.com/conda-forge/boost-histogram-feedstock/pull/58",
 "id": 2308018595,
 "labels": [],
 "last_modified": null,
 "mergeable": null,
 "mergeable_state": "unknown",
 "merged": true,
 "merged_at": "2025-01-31T00:41:57Z",
 "number": 58,
 "state": "closed",
 "updated_at": "2025-01-31T00:42:01Z"
}