{
 "base": {
  "repo": {
   "name": "translators-feedstock"
  }
 },
 "closed_at": null,
 "created_at": "2025-01-27T12:31:55Z",
 "draft": false,
 "e_tag": "\"67429666ea9d1b084131ddcff5a6190a836ca6cd7e430731593e7862f8d69259\"",
 "head": {
  "ref": "5.9.5_h3f4302"
 },
 "html_url": "https://github.com/conda-forge/translators-feedstock/pull/26",
 "id": 2299797762,
 "labels": [],
 "last_modified": null,
 "mergeable": null,
 "mergeable_state": "unknown",
 "merged": false,
 "merged_at": null,
 "number": 26,
 "state": "open",
 "updated_at": "2025-01-27T12:31:55Z"
}