{
 "base": {
  "repo": {
   "name": "jj-feedstock"
  }
 },
 "closed_at": null,
 "created_at": "2025-02-06T10:43:47Z",
 "draft": false,
 "e_tag": "\"e0573c65bf440dce891fc0539ab5d0ea34d87ef7a0fb40ed3facd1eadc9aa3cd\"",
 "head": {
  "ref": "0.26.0_hc7358f"
 },
 "html_url": "https://github.com/conda-forge/jj-feedstock/pull/7",
 "id": 2319591801,
 "labels": [],
 "last_modified": null,
 "mergeable": null,
 "mergeable_state": "unknown",
 "merged": false,
 "merged_at": null,
 "number": 7,
 "state": "open",
 "updated_at": "2025-02-06T10:43:47Z"
}