{
 "ETag": "W/\"a5ab8e4b600ba011d905a0de8cd54e1db52fcd987df8251d1111ea175f615488\"",
 "Last-Modified": "Tue, 28 Jan 2025 16:23:49 GMT",
 "base": {
  "repo": {
   "name": "pydataverse-feedstock"
  }
 },
 "closed_at": "2025-01-28T16:23:47Z",
 "created_at": "2024-12-30T11:30:36Z",
 "draft": false,
 "e_tag": "\"285f1be7c0a1a50154dc7d59459e3e6afae0dba1d9e2b500f0e264c7bfafa18d\"",
 "head": {
  "ref": "noarch_python_min-migration-1_h0dc414"
 },
 "html_url": "https://github.com/conda-forge/pydataverse-feedstock/pull/5",
 "id": 2255307998,
 "labels": [
  {
   "color": "191970",
   "default": false,
   "description": "Instruct the bot to retry the PR",
   "id": 5540034619,
   "name": "bot-rerun",
   "node_id": "LA_kwDOJm-UQ88AAAABSjY4Ow",
   "url": "https://api.github.com/repos/conda-forge/pydataverse-feedstock/labels/bot-rerun"
  }
 ],
 "last_modified": null,
 "mergeable": false,
 "mergeable_state": "dirty",
 "merged": false,
 "merged_at": null,
 "number": 5,
 "state": "closed",
 "updated_at": "2025-01-28T16:23:49Z"
}