{
 "base": {
  "repo": {
   "name": "robotframework-databaselibrary-feedstock"
  }
 },
 "closed_at": null,
 "created_at": "2025-02-04T16:17:07Z",
 "draft": false,
 "e_tag": "\"4415705d3d006d421374dfcacde5a5bab7f2a0436f0b764abf3a05447daf553b\"",
 "head": {
  "ref": "2.1.0_h77814f"
 },
 "html_url": "https://github.com/conda-forge/robotframework-databaselibrary-feedstock/pull/13",
 "id": 2315630203,
 "labels": [],
 "last_modified": null,
 "mergeable": null,
 "mergeable_state": "unknown",
 "merged": false,
 "merged_at": null,
 "number": 13,
 "state": "open",
 "updated_at": "2025-02-04T16:17:07Z"
}