{
 "base": {
  "repo": {
   "name": "pyseidon-feedstock"
  }
 },
 "closed_at": null,
 "created_at": "2025-01-26T13:44:39Z",
 "draft": false,
 "e_tag": "\"305b9134d30b386fb50f90cc2d5917a84e65df608927a00a2dab249750b5326b\"",
 "head": {
  "ref": "noarch_python_min-migration-1_hb9419e"
 },
 "html_url": "https://github.com/conda-forge/pyseidon-feedstock/pull/8",
 "id": 2298631212,
 "labels": [],
 "last_modified": null,
 "mergeable": null,
 "mergeable_state": "unknown",
 "merged": false,
 "merged_at": null,
 "number": 8,
 "state": "open",
 "updated_at": "2025-01-26T13:44:39Z"
}