{
 "ETag": "W/\"08799d2d472125deb0a885e70c02224ba70ad267972713d32a0ef20c8f5f7491\"",
 "Last-Modified": "Tue, 04 Feb 2025 07:35:26 GMT",
 "base": {
  "repo": {
   "name": "xenv-feedstock"
  }
 },
 "closed_at": null,
 "created_at": "2025-02-04T00:32:40Z",
 "draft": false,
 "e_tag": "\"fdc7b099a300da77277b1e86f1c3c73e6d9b45165588bac32c56a09570c05765\"",
 "head": {
  "ref": "noarch_python_min-migration-1_hb26df2"
 },
 "html_url": "https://github.com/conda-forge/xenv-feedstock/pull/14",
 "id": 2313938471,
 "labels": [
  {
   "color": "0e8a16",
   "default": false,
   "description": "Merge the PR when CI passes",
   "id": 1891429220,
   "name": "automerge",
   "node_id": "MDU6TGFiZWwxODkxNDI5MjIw",
   "url": "https://api.github.com/repos/conda-forge/xenv-feedstock/labels/automerge"
  }
 ],
 "last_modified": null,
 "mergeable": true,
 "mergeable_state": "unstable",
 "merged": false,
 "merged_at": null,
 "number": 14,
 "state": "open",
 "updated_at": "2025-02-04T07:35:26Z"
}