{
 "base": {
  "repo": {
   "name": "rio-tiler-feedstock"
  }
 },
 "closed_at": null,
 "created_at": "2025-01-28T17:43:28Z",
 "draft": false,
 "e_tag": "\"f217f5085a539eeaaa753ba4cf9e048fb99fce17d114314ad0283462d4acdcda\"",
 "head": {
  "ref": "7.4.0_hc57154"
 },
 "html_url": "https://github.com/conda-forge/rio-tiler-feedstock/pull/81",
 "id": 2302891719,
 "labels": [],
 "last_modified": null,
 "mergeable": null,
 "mergeable_state": "unknown",
 "merged": false,
 "merged_at": null,
 "number": 81,
 "state": "open",
 "updated_at": "2025-01-28T17:43:28Z"
}