{
 "base": {
  "repo": {
   "name": "hypothesis-feedstock"
  }
 },
 "closed_at": null,
 "created_at": "2025-01-25T08:02:09Z",
 "draft": false,
 "e_tag": "\"807531b92b59cee5601c3c0fc5b07ba5ddcf80328f6a8e3e1dc07b085049fb2b\"",
 "head": {
  "ref": "6.124.4_hd7a4ed"
 },
 "html_url": "https://github.com/conda-forge/hypothesis-feedstock/pull/1008",
 "id": 2298027112,
 "labels": [],
 "last_modified": null,
 "mergeable": null,
 "mergeable_state": "unknown",
 "merged": false,
 "merged_at": null,
 "number": 1008,
 "state": "open",
 "updated_at": "2025-01-25T08:02:09Z"
}