{
 "ETag": "W/\"ea00b8eddc11235ee54811ae79b3498d6f59f3ead13a169ea82d9cee378479d0\"",
 "Last-Modified": "Sun, 26 Jan 2025 04:39:02 GMT",
 "base": {
  "repo": {
   "name": "av-feedstock"
  }
 },
 "closed_at": null,
 "created_at": "2025-01-26T04:09:40Z",
 "draft": false,
 "e_tag": "\"574c6318f8c5cb704ae49327281ec7cb361c007a2acf1fcc6f356432b9262593\"",
 "head": {
  "ref": "14.1.0_hb9cf6b"
 },
 "html_url": "https://github.com/conda-forge/av-feedstock/pull/86",
 "id": 2298408161,
 "labels": [],
 "last_modified": null,
 "mergeable": true,
 "mergeable_state": "clean",
 "merged": false,
 "merged_at": null,
 "number": 86,
 "state": "open",
 "updated_at": "2025-01-26T04:39:02Z"
}