{
 "ETag": "W/\"664858f796440a5793f5c0d1169520df782a3b3656fb92a36c6f8fe25f931bef\"",
 "Last-Modified": "Fri, 31 Jan 2025 07:38:18 GMT",
 "base": {
  "repo": {
   "name": "geetools-feedstock"
  }
 },
 "closed_at": "2025-01-31T07:38:18Z",
 "created_at": "2025-01-31T05:09:30Z",
 "draft": false,
 "e_tag": "\"9365844445275fa94331062b1997bdaaf6e0453445b59bcc44af4ba8268bac3c\"",
 "head": {
  "ref": "this_is_not_a_branch"
 },
 "html_url": "https://github.com/conda-forge/geetools-feedstock/pull/19",
 "id": 2308288826,
 "labels": [],
 "last_modified": null,
 "mergeable": null,
 "mergeable_state": "unknown",
 "merged": true,
 "merged_at": "2025-01-31T07:38:18Z",
 "number": 19,
 "state": "closed",
 "updated_at": "2025-01-31T07:38:18Z"
}