{
 "ETag": "W/\"74014fe53fa62b2c6efc9bf540da6023b1db63bbe3d4873da4fdab1b27582398\"",
 "Last-Modified": "Mon, 27 Jan 2025 20:41:16 GMT",
 "base": {
  "repo": {
   "name": "storybook-feedstock"
  }
 },
 "closed_at": "2025-01-27T20:40:40Z",
 "created_at": "2025-01-27T20:36:54Z",
 "draft": false,
 "e_tag": "\"808704806ab53d6b55409d44e2fff56ac953b7201e8f95d228450564deec6b3e\"",
 "head": {
  "ref": "this_is_not_a_branch"
 },
 "html_url": "https://github.com/conda-forge/storybook-feedstock/pull/4",
 "id": 2300790482,
 "labels": [],
 "last_modified": null,
 "mergeable": null,
 "mergeable_state": "unknown",
 "merged": true,
 "merged_at": "2025-01-27T20:40:39Z",
 "number": 4,
 "state": "closed",
 "updated_at": "2025-01-27T20:41:16Z"
}