{
 "ETag": "W/\"b21b48f82e88e132f327e70b5d9630785bd7174027e35b48d7f49d2e8667bdf5\"",
 "Last-Modified": "Sat, 01 Feb 2025 00:54:56 GMT",
 "base": {
  "repo": {
   "name": "boto3-feedstock"
  }
 },
 "closed_at": null,
 "created_at": "2025-01-31T22:11:28Z",
 "draft": false,
 "e_tag": "\"321ad4cdc153e6627643f1f52c60d40fadaf91fead2e6a8daca37d1bfe3c2846\"",
 "head": {
  "ref": "1.36.11_h911b4d"
 },
 "html_url": "https://github.com/conda-forge/boto3-feedstock/pull/1703",
 "id": 2310106775,
 "labels": [],
 "last_modified": null,
 "mergeable": true,
 "mergeable_state": "unstable",
 "merged": false,
 "merged_at": null,
 "number": 1703,
 "state": "open",
 "updated_at": "2025-02-01T00:54:56Z"
}