{
  "_feedstock_status": {
    "cds-crtools": {
      "immediate_children": [],
      "num_descendants": 0,
      "pre_pr_migrator_status": "not solvable (<a href='https://github.com/regro/cf-scripts/actions/runs/13202547225'>bot CI job</a>) @ main\n        <details>\n        <div align=\"left\">\n        <pre>\n        linux_64_: Cannot solve the request because of: root_base 6.32.8.* cannot be installed because there are no viable options:\n\u2514\u2500 root_base 6.32.8 | 6.32.8 | 6.32.8 | 6.32.8 | 6.32.8 would require\n   \u2514\u2500 pythia8 >=8.312,<8.400.0a0, which cannot be installed because there are no viable options:\n      \u251C\u2500 pythia8 8.312 | 8.312 | 8.312 would require\n      \u2502  \u2514\u2500 _x86_64-microarch-level >=3, which cannot be installed because there are no viable options:\n      \u2502     \u2514\u2500 _x86_64-microarch-level 3 | 3 | 3 | 3 | 3 | 3 | 3 | 3 | 3 | 3 | 3 | 3 | 3 | 3 | 3 | 3 | 3 | 3 | 3 | 3 | 3 | 3 | 3 | 3 | 3 | 3 | 3 | 3 | 3 | 3 | 4 | 4 | 4 | 4 | 4 | 4 | 4 | 4 | 4 | 4 | 4 | 4 | 4 | 4 | 4 | 4 | 4 | 4 would require\n      \u2502        \u2514\u2500 __archspec ==1 cannonlake, for which no candidates were found.\n      \u251C\u2500 pythia8 8.312 | 8.312 | 8.312 would require\n      \u2502  \u2514\u2500 _x86_64-microarch-level >=1, which cannot be installed because there are no viable options:\n      \u2502     \u2514\u2500 _x86_64-microarch-level 1 | 1 | 1 | 1 | 1 | 1 | 1 | 1 | 1 | 1 | 1 | 1 | 2 | 2 | 2 | 2 | 2 | 2 | 2 | 2 | 2 | 2 | 2 | 2 | 2 | 2 | 2 | 2 | 2 | 2 | 2 | 2 | 2 | 2 | 2 | 2 would require\n      \u2502        \u2514\u2500 __archspec ==1 core2, for which no candidates were found.\n      \u2514\u2500 pythia8 8.312 | 8.312 | 8.312 | 8.312 | 8.312 | 8.312 | 8.312 | 8.312 | 8.312 | 8.312 | 8.312 | 8.312 | 8.312 | 8.312 | 8.312 | 8.312 | 8.312 | 8.312 | 8.312 | 8.312 | 8.312 | 8.312 | 8.312 | 8.312 would require\n         \u2514\u2500 python >=3.10,<3.11.0a0, for which no candidates were found.\n</pre><pre>linux_64_: Cannot solve the request because of: root_base 6.32.8.* cannot be installed because there are no viable options:\n\u2514\u2500 root_base 6.32.8 | 6.32.8 | 6.32.8 | 6.32.8 | 6.32.8 would require\n   \u2514\u2500 pythia8 >=8.312,<8.400.0a0, which cannot be installed because there are no viable options:\n      \u251C\u2500 pythia8 8.312 | 8.312 | 8.312 would require\n      \u2502  \u2514\u2500 _x86_64-microarch-level >=3, which cannot be installed because there are no viable options:\n      \u2502     \u2514\u2500 _x86_64-microarch-level 3 | 3 | 3 | 3 | 3 | 3 | 3 | 3 | 3 | 3 | 3 | 3 | 3 | 3 | 3 | 3 | 3 | 3 | 3 | 3 | 3 | 3 | 3 | 3 | 3 | 3 | 3 | 3 | 3 | 3 | 4 | 4 | 4 | 4 | 4 | 4 | 4 | 4 | 4 | 4 | 4 | 4 | 4 | 4 | 4 | 4 | 4 | 4 would require\n      \u2502        \u2514\u2500 __archspec ==1 cannonlake, for which no candidates were found.\n      \u251C\u2500 pythia8 8.312 | 8.312 | 8.312 would require\n      \u2502  \u2514\u2500 _x86_64-microarch-level >=1, which cannot be installed because there are no viable options:\n      \u2502     \u2514\u2500 _x86_64-microarch-level 1 | 1 | 1 | 1 | 1 | 1 | 1 | 1 | 1 | 1 | 1 | 1 | 2 | 2 | 2 | 2 | 2 | 2 | 2 | 2 | 2 | 2 | 2 | 2 | 2 | 2 | 2 | 2 | 2 | 2 | 2 | 2 | 2 | 2 | 2 | 2 would require\n      \u2502        \u2514\u2500 __archspec ==1 core2, for which no candidates were found.\n      \u2514\u2500 pythia8 8.312 | 8.312 | 8.312 | 8.312 | 8.312 | 8.312 | 8.312 | 8.312 | 8.312 | 8.312 | 8.312 | 8.312 | 8.312 | 8.312 | 8.312 | 8.312 | 8.312 | 8.312 | 8.312 | 8.312 | 8.312 | 8.312 | 8.312 | 8.312 would require\n         \u2514\u2500 python >=3.9,<3.10.0a0, for which no candidates were found.\n</pre><pre>linux_64_: Cannot solve the request because of: root_base 6.32.8.* cannot be installed because there are no viable options:\n\u2514\u2500 root_base 6.32.8 | 6.32.8 | 6.32.8 | 6.32.8 | 6.32.8 would require\n   \u2514\u2500 pythia8 >=8.312,<8.400.0a0, which cannot be installed because there are no viable options:\n      \u251C\u2500 pythia8 8.312 | 8.312 | 8.312 | 8.312 | 8.312 | 8.312 | 8.312 | 8.312 | 8.312 | 8.312 | 8.312 | 8.312 | 8.312 | 8.312 | 8.312 would require\n      \u2502  \u2514\u2500 _x86_64-microarch-level >=3, which cannot be installed because there are no viable options:\n      \u2502     \u2514\u2500 _x86_64-microarch-level 3 | 3 | 3 | 3 | 3 | 3 | 3 | 3 | 3 | 3 | 3 | 3 | 3 | 3 | 3 | 3 | 3 | 3 | 3 | 3 | 3 | 3 | 3 | 3 | 3 | 3 | 3 | 3 | 3 | 3 | 4 | 4 | 4 | 4 | 4 | 4 | 4 | 4 | 4 | 4 | 4 | 4 | 4 | 4 | 4 | 4 | 4 | 4 would require\n      \u2502        \u2514\u2500 __archspec ==1 cannonlake, for which no candidates were found.\n      \u2514\u2500 pythia8 8.312 | 8.312 | 8.312 | 8.312 | 8.312 | 8.312 | 8.312 | 8.312 | 8.312 | 8.312 | 8.312 | 8.312 | 8.312 | 8.312 | 8.312 would require\n         \u2514\u2500 _x86_64-microarch-level >=1, which cannot be installed because there are no viable options:\n            \u2514\u2500 _x86_64-microarch-level 1 | 1 | 1 | 1 | 1 | 1 | 1 | 1 | 1 | 1 | 1 | 1 | 2 | 2 | 2 | 2 | 2 | 2 | 2 | 2 | 2 | 2 | 2 | 2 | 2 | 2 | 2 | 2 | 2 | 2 | 2 | 2 | 2 | 2 | 2 | 2 would require\n               \u2514\u2500 __archspec ==1 core2, for which no candidates were found.\n\n        </pre>\n        </div>\n        </details>"
    },
    "cwb": {
      "immediate_children": [],
      "num_descendants": 0,
      "pr_status": "unknown",
      "pr_url": "https://github.com/conda-forge/cwb-feedstock/pull/30",
      "pre_pr_migrator_status": ""
    },
    "delphes": {
      "immediate_children": [],
      "num_descendants": 0,
      "pr_status": "unknown",
      "pr_url": "https://github.com/conda-forge/delphes-feedstock/pull/7",
      "pre_pr_migrator_status": ""
    },
    "gds-dmt": {
      "immediate_children": [
        "gds-monitor-apps"
      ],
      "num_descendants": 1,
      "pre_pr_migrator_status": "not solvable (<a href='https://github.com/regro/cf-scripts/actions/runs/13200643317'>bot CI job</a>) @ main\n        <details>\n        <div align=\"left\">\n        <pre>\n        linux_64_: Cannot solve the request because of: root_base 6.32.8.* cannot be installed because there are no viable options:\n\u2514\u2500 root_base 6.32.8 | 6.32.8 | 6.32.8 | 6.32.8 | 6.32.8 would require\n   \u2514\u2500 pythia8 >=8.312,<8.400.0a0, which cannot be installed because there are no viable options:\n      \u251C\u2500 pythia8 8.312 | 8.312 | 8.312 | 8.312 | 8.312 | 8.312 | 8.312 | 8.312 | 8.312 | 8.312 | 8.312 | 8.312 | 8.312 | 8.312 | 8.312 would require\n      \u2502  \u2514\u2500 _x86_64-microarch-level >=3, which cannot be installed because there are no viable options:\n      \u2502     \u2514\u2500 _x86_64-microarch-level 3 | 3 | 3 | 3 | 3 | 3 | 3 | 3 | 3 | 3 | 3 | 3 | 3 | 3 | 3 | 3 | 3 | 3 | 3 | 3 | 3 | 3 | 3 | 3 | 3 | 3 | 3 | 3 | 3 | 3 | 4 | 4 | 4 | 4 | 4 | 4 | 4 | 4 | 4 | 4 | 4 | 4 | 4 | 4 | 4 | 4 | 4 | 4 would require\n      \u2502        \u2514\u2500 __archspec ==1 cannonlake, for which no candidates were found.\n      \u2514\u2500 pythia8 8.312 | 8.312 | 8.312 | 8.312 | 8.312 | 8.312 | 8.312 | 8.312 | 8.312 | 8.312 | 8.312 | 8.312 | 8.312 | 8.312 | 8.312 would require\n         \u2514\u2500 _x86_64-microarch-level >=1, which cannot be installed because there are no viable options:\n            \u2514\u2500 _x86_64-microarch-level 1 | 1 | 1 | 1 | 1 | 1 | 1 | 1 | 1 | 1 | 1 | 1 | 2 | 2 | 2 | 2 | 2 | 2 | 2 | 2 | 2 | 2 | 2 | 2 | 2 | 2 | 2 | 2 | 2 | 2 | 2 | 2 | 2 | 2 | 2 | 2 would require\n               \u2514\u2500 __archspec ==1 core2, for which no candidates were found.\n</pre><pre>osx_64_: Cannot solve the request because of: root_base 6.32.8.* cannot be installed because there are no viable options:\n\u2514\u2500 root_base 6.32.8 | 6.32.8 | 6.32.8 | 6.32.8 | 6.32.8 would require\n   \u2514\u2500 pythia8 >=8.312,<8.400.0a0, which cannot be installed because there are no viable options:\n      \u251C\u2500 pythia8 8.312 | 8.312 | 8.312 | 8.312 | 8.312 | 8.312 | 8.312 | 8.312 | 8.312 | 8.312 | 8.312 | 8.312 | 8.312 | 8.312 | 8.312 would require\n      \u2502  \u2514\u2500 _x86_64-microarch-level >=3, which cannot be installed because there are no viable options:\n      \u2502     \u2514\u2500 _x86_64-microarch-level 3 | 3 | 3 | 3 | 3 | 3 | 3 | 3 | 3 | 3 | 3 | 3 | 3 | 3 | 3 | 3 | 3 | 3 | 3 | 3 | 3 | 3 | 3 | 3 | 3 | 3 | 3 | 3 | 3 | 3 | 4 | 4 | 4 | 4 | 4 | 4 | 4 | 4 | 4 | 4 | 4 | 4 | 4 | 4 | 4 | 4 | 4 | 4 would require\n      \u2502        \u2514\u2500 __archspec ==1 cannonlake, for which no candidates were found.\n      \u2514\u2500 pythia8 8.312 | 8.312 | 8.312 | 8.312 | 8.312 | 8.312 | 8.312 | 8.312 | 8.312 | 8.312 | 8.312 | 8.312 | 8.312 | 8.312 | 8.312 would require\n         \u2514\u2500 _x86_64-microarch-level >=1, which cannot be installed because there are no viable options:\n            \u2514\u2500 _x86_64-microarch-level 1 | 1 | 1 | 1 | 1 | 1 | 1 | 1 | 1 | 1 | 1 | 1 | 2 | 2 | 2 | 2 | 2 | 2 | 2 | 2 | 2 | 2 | 2 | 2 | 2 | 2 | 2 | 2 | 2 | 2 | 2 | 2 | 2 | 2 | 2 | 2 would require\n               \u2514\u2500 __archspec ==1 core2, for which no candidates were found.\n\n        </pre>\n        </div>\n        </details>"
    },
    "gds-gui": {
      "immediate_children": [
        "gds-monitor-apps"
      ],
      "num_descendants": 1,
      "pr_status": "unknown",
      "pr_url": "https://github.com/conda-forge/gds-gui-feedstock/pull/26",
      "pre_pr_migrator_status": ""
    },
    "gds-monitor-apps": {
      "immediate_children": [],
      "num_descendants": 0,
      "pre_pr_migrator_status": ""
    },
    "gds-root-extensions": {
      "immediate_children": [
        "cds-crtools"
      ],
      "num_descendants": 1,
      "pr_status": "",
      "pr_url": "https://github.com/conda-forge/gds-root-extensions-feedstock",
      "pre_pr_migrator_status": ""
    },
    "gwollum": {
      "immediate_children": [
        "omicron",
        "upv",
        "vetoperf"
      ],
      "num_descendants": 3,
      "pre_pr_migrator_status": "not solvable (<a href='https://github.com/regro/cf-scripts/actions/runs/13202547225'>bot CI job</a>) @ main\n        <details>\n        <div align=\"left\">\n        <pre>\n        linux_64_: Cannot solve the request because of: root_base 6.32.8.* cannot be installed because there are no viable options:\n\u2514\u2500 root_base 6.32.8 | 6.32.8 | 6.32.8 | 6.32.8 | 6.32.8 would require\n   \u2514\u2500 pythia8 >=8.312,<8.400.0a0, which cannot be installed because there are no viable options:\n      \u251C\u2500 pythia8 8.312 | 8.312 | 8.312 | 8.312 | 8.312 | 8.312 | 8.312 | 8.312 | 8.312 | 8.312 | 8.312 | 8.312 | 8.312 | 8.312 | 8.312 would require\n      \u2502  \u2514\u2500 _x86_64-microarch-level >=3, which cannot be installed because there are no viable options:\n      \u2502     \u2514\u2500 _x86_64-microarch-level 3 | 3 | 3 | 3 | 3 | 3 | 3 | 3 | 3 | 3 | 3 | 3 | 3 | 3 | 3 | 3 | 3 | 3 | 3 | 3 | 3 | 3 | 3 | 3 | 3 | 3 | 3 | 3 | 3 | 3 | 4 | 4 | 4 | 4 | 4 | 4 | 4 | 4 | 4 | 4 | 4 | 4 | 4 | 4 | 4 | 4 | 4 | 4 would require\n      \u2502        \u2514\u2500 __archspec ==1 cannonlake, for which no candidates were found.\n      \u2514\u2500 pythia8 8.312 | 8.312 | 8.312 | 8.312 | 8.312 | 8.312 | 8.312 | 8.312 | 8.312 | 8.312 | 8.312 | 8.312 | 8.312 | 8.312 | 8.312 would require\n         \u2514\u2500 _x86_64-microarch-level >=1, which cannot be installed because there are no viable options:\n            \u2514\u2500 _x86_64-microarch-level 1 | 1 | 1 | 1 | 1 | 1 | 1 | 1 | 1 | 1 | 1 | 1 | 2 | 2 | 2 | 2 | 2 | 2 | 2 | 2 | 2 | 2 | 2 | 2 | 2 | 2 | 2 | 2 | 2 | 2 | 2 | 2 | 2 | 2 | 2 | 2 would require\n               \u2514\u2500 __archspec ==1 core2, for which no candidates were found.\n</pre><pre>osx_64_: Cannot solve the request because of: root_base 6.32.8.* cannot be installed because there are no viable options:\n\u2514\u2500 root_base 6.32.8 | 6.32.8 | 6.32.8 | 6.32.8 | 6.32.8 would require\n   \u2514\u2500 pythia8 >=8.312,<8.400.0a0, which cannot be installed because there are no viable options:\n      \u251C\u2500 pythia8 8.312 | 8.312 | 8.312 | 8.312 | 8.312 | 8.312 | 8.312 | 8.312 | 8.312 | 8.312 | 8.312 | 8.312 | 8.312 | 8.312 | 8.312 would require\n      \u2502  \u2514\u2500 _x86_64-microarch-level >=3, which cannot be installed because there are no viable options:\n      \u2502     \u2514\u2500 _x86_64-microarch-level 3 | 3 | 3 | 3 | 3 | 3 | 3 | 3 | 3 | 3 | 3 | 3 | 3 | 3 | 3 | 3 | 3 | 3 | 3 | 3 | 3 | 3 | 3 | 3 | 3 | 3 | 3 | 3 | 3 | 3 | 4 | 4 | 4 | 4 | 4 | 4 | 4 | 4 | 4 | 4 | 4 | 4 | 4 | 4 | 4 | 4 | 4 | 4 would require\n      \u2502        \u2514\u2500 __archspec ==1 cannonlake, for which no candidates were found.\n      \u2514\u2500 pythia8 8.312 | 8.312 | 8.312 | 8.312 | 8.312 | 8.312 | 8.312 | 8.312 | 8.312 | 8.312 | 8.312 | 8.312 | 8.312 | 8.312 | 8.312 would require\n         \u2514\u2500 _x86_64-microarch-level >=1, which cannot be installed because there are no viable options:\n            \u2514\u2500 _x86_64-microarch-level 1 | 1 | 1 | 1 | 1 | 1 | 1 | 1 | 1 | 1 | 1 | 1 | 2 | 2 | 2 | 2 | 2 | 2 | 2 | 2 | 2 | 2 | 2 | 2 | 2 | 2 | 2 | 2 | 2 | 2 | 2 | 2 | 2 | 2 | 2 | 2 would require\n               \u2514\u2500 __archspec ==1 core2, for which no candidates were found.\n\n        </pre>\n        </div>\n        </details>"
    },
    "hammer": {
      "immediate_children": [],
      "num_descendants": 0,
      "pre_pr_migrator_status": "not solvable (<a href='https://github.com/regro/cf-scripts/actions/runs/13202547225'>bot CI job</a>) @ main\n        <details>\n        <div align=\"left\">\n        <pre>\n        linux_64_numpy1.22python3.10.____cpython: Cannot solve the request because of: root_base 6.32.8.* cannot be installed because there are no viable options:\n\u2514\u2500 root_base 6.32.8 | 6.32.8 | 6.32.8 | 6.32.8 | 6.32.8 would require\n   \u2514\u2500 pythia8 >=8.312,<8.400.0a0, which cannot be installed because there are no viable options:\n      \u251C\u2500 pythia8 8.312 | 8.312 | 8.312 would require\n      \u2502  \u2514\u2500 _x86_64-microarch-level >=3, which cannot be installed because there are no viable options:\n      \u2502     \u2514\u2500 _x86_64-microarch-level 3 | 3 | 3 | 3 | 3 | 3 | 3 | 3 | 3 | 3 | 3 | 3 | 3 | 3 | 3 | 3 | 3 | 3 | 3 | 3 | 3 | 3 | 3 | 3 | 3 | 3 | 3 | 3 | 3 | 3 | 4 | 4 | 4 | 4 | 4 | 4 | 4 | 4 | 4 | 4 | 4 | 4 | 4 | 4 | 4 | 4 | 4 | 4 would require\n      \u2502        \u2514\u2500 __archspec ==1 cannonlake, for which no candidates were found.\n      \u251C\u2500 pythia8 8.312 | 8.312 | 8.312 would require\n      \u2502  \u2514\u2500 _x86_64-microarch-level >=1, which cannot be installed because there are no viable options:\n      \u2502     \u2514\u2500 _x86_64-microarch-level 1 | 1 | 1 | 1 | 1 | 1 | 1 | 1 | 1 | 1 | 1 | 1 | 2 | 2 | 2 | 2 | 2 | 2 | 2 | 2 | 2 | 2 | 2 | 2 | 2 | 2 | 2 | 2 | 2 | 2 | 2 | 2 | 2 | 2 | 2 | 2 would require\n      \u2502        \u2514\u2500 __archspec ==1 core2, for which no candidates were found.\n      \u2514\u2500 pythia8 8.312 | 8.312 | 8.312 | 8.312 | 8.312 | 8.312 | 8.312 | 8.312 | 8.312 | 8.312 | 8.312 | 8.312 | 8.312 | 8.312 | 8.312 | 8.312 | 8.312 | 8.312 | 8.312 | 8.312 | 8.312 | 8.312 | 8.312 | 8.312 would require\n         \u2514\u2500 python >=3.9,<3.10.0a0, for which no candidates were found.\n</pre><pre>linux_64_numpy1.22python3.9.____cpython: Cannot solve the request because of: root_base 6.32.8.* cannot be installed because there are no viable options:\n\u2514\u2500 root_base 6.32.8 | 6.32.8 | 6.32.8 | 6.32.8 | 6.32.8 would require\n   \u2514\u2500 pythia8 >=8.312,<8.400.0a0, which cannot be installed because there are no viable options:\n      \u251C\u2500 pythia8 8.312 | 8.312 | 8.312 would require\n      \u2502  \u2514\u2500 _x86_64-microarch-level >=3, which cannot be installed because there are no viable options:\n      \u2502     \u2514\u2500 _x86_64-microarch-level 3 | 3 | 3 | 3 | 3 | 3 | 3 | 3 | 3 | 3 | 3 | 3 | 3 | 3 | 3 | 3 | 3 | 3 | 3 | 3 | 3 | 3 | 3 | 3 | 3 | 3 | 3 | 3 | 3 | 3 | 4 | 4 | 4 | 4 | 4 | 4 | 4 | 4 | 4 | 4 | 4 | 4 | 4 | 4 | 4 | 4 | 4 | 4 would require\n      \u2502        \u2514\u2500 __archspec ==1 cannonlake, for which no candidates were found.\n      \u251C\u2500 pythia8 8.312 | 8.312 | 8.312 would require\n      \u2502  \u2514\u2500 _x86_64-microarch-level >=1, which cannot be installed because there are no viable options:\n      \u2502     \u2514\u2500 _x86_64-microarch-level 1 | 1 | 1 | 1 | 1 | 1 | 1 | 1 | 1 | 1 | 1 | 1 | 2 | 2 | 2 | 2 | 2 | 2 | 2 | 2 | 2 | 2 | 2 | 2 | 2 | 2 | 2 | 2 | 2 | 2 | 2 | 2 | 2 | 2 | 2 | 2 would require\n      \u2502        \u2514\u2500 __archspec ==1 core2, for which no candidates were found.\n      \u2514\u2500 pythia8 8.312 | 8.312 | 8.312 | 8.312 | 8.312 | 8.312 | 8.312 | 8.312 | 8.312 | 8.312 | 8.312 | 8.312 | 8.312 | 8.312 | 8.312 | 8.312 | 8.312 | 8.312 | 8.312 | 8.312 | 8.312 | 8.312 | 8.312 | 8.312 would require\n         \u2514\u2500 python >=3.10,<3.11.0a0, for which no candidates were found.\n</pre><pre>linux_64_numpy1.23python3.11.____cpython: Cannot solve the request because of: root_base 6.32.8.* cannot be installed because there are no viable options:\n\u2514\u2500 root_base 6.32.8 | 6.32.8 | 6.32.8 | 6.32.8 | 6.32.8 would require\n   \u2514\u2500 pythia8 >=8.312,<8.400.0a0, which cannot be installed because there are no viable options:\n      \u251C\u2500 pythia8 8.312 | 8.312 | 8.312 would require\n      \u2502  \u2514\u2500 _x86_64-microarch-level >=3, which cannot be installed because there are no viable options:\n      \u2502     \u2514\u2500 _x86_64-microarch-level 3 | 3 | 3 | 3 | 3 | 3 | 3 | 3 | 3 | 3 | 3 | 3 | 3 | 3 | 3 | 3 | 3 | 3 | 3 | 3 | 3 | 3 | 3 | 3 | 3 | 3 | 3 | 3 | 3 | 3 | 4 | 4 | 4 | 4 | 4 | 4 | 4 | 4 | 4 | 4 | 4 | 4 | 4 | 4 | 4 | 4 | 4 | 4 would require\n      \u2502        \u2514\u2500 __archspec ==1 cannonlake, for which no candidates were found.\n      \u251C\u2500 pythia8 8.312 | 8.312 | 8.312 would require\n      \u2502  \u2514\u2500 _x86_64-microarch-level >=1, which cannot be installed because there are no viable options:\n      \u2502     \u2514\u2500 _x86_64-microarch-level 1 | 1 | 1 | 1 | 1 | 1 | 1 | 1 | 1 | 1 | 1 | 1 | 2 | 2 | 2 | 2 | 2 | 2 | 2 | 2 | 2 | 2 | 2 | 2 | 2 | 2 | 2 | 2 | 2 | 2 | 2 | 2 | 2 | 2 | 2 | 2 would require\n      \u2502        \u2514\u2500 __archspec ==1 core2, for which no candidates were found.\n      \u2514\u2500 pythia8 8.312 | 8.312 | 8.312 | 8.312 | 8.312 | 8.312 | 8.312 | 8.312 | 8.312 | 8.312 | 8.312 | 8.312 | 8.312 | 8.312 | 8.312 | 8.312 | 8.312 | 8.312 | 8.312 | 8.312 | 8.312 | 8.312 | 8.312 | 8.312 would require\n         \u2514\u2500 python >=3.9,<3.10.0a0, for which no candidates were found.\n</pre><pre>linux_64_numpy1.26python3.12.____cpython: Cannot solve the request because of: root_base 6.32.8.* cannot be installed because there are no viable options:\n\u2514\u2500 root_base 6.32.8 | 6.32.8 | 6.32.8 | 6.32.8 | 6.32.8 would require\n   \u2514\u2500 pythia8 >=8.312,<8.400.0a0, which cannot be installed because there are no viable options:\n      \u251C\u2500 pythia8 8.312 | 8.312 | 8.312 would require\n      \u2502  \u2514\u2500 _x86_64-microarch-level >=3, which cannot be installed because there are no viable options:\n      \u2502     \u2514\u2500 _x86_64-microarch-level 3 | 3 | 3 | 3 | 3 | 3 | 3 | 3 | 3 | 3 | 3 | 3 | 3 | 3 | 3 | 3 | 3 | 3 | 3 | 3 | 3 | 3 | 3 | 3 | 3 | 3 | 3 | 3 | 3 | 3 | 4 | 4 | 4 | 4 | 4 | 4 | 4 | 4 | 4 | 4 | 4 | 4 | 4 | 4 | 4 | 4 | 4 | 4 would require\n      \u2502        \u2514\u2500 __archspec ==1 cannonlake, for which no candidates were found.\n      \u251C\u2500 pythia8 8.312 | 8.312 | 8.312 would require\n      \u2502  \u2514\u2500 _x86_64-microarch-level >=1, which cannot be installed because there are no viable options:\n      \u2502     \u2514\u2500 _x86_64-microarch-level 1 | 1 | 1 | 1 | 1 | 1 | 1 | 1 | 1 | 1 | 1 | 1 | 2 | 2 | 2 | 2 | 2 | 2 | 2 | 2 | 2 | 2 | 2 | 2 | 2 | 2 | 2 | 2 | 2 | 2 | 2 | 2 | 2 | 2 | 2 | 2 would require\n      \u2502        \u2514\u2500 __archspec ==1 core2, for which no candidates were found.\n      \u2514\u2500 pythia8 8.312 | 8.312 | 8.312 | 8.312 | 8.312 | 8.312 | 8.312 | 8.312 | 8.312 | 8.312 | 8.312 | 8.312 | 8.312 | 8.312 | 8.312 | 8.312 | 8.312 | 8.312 | 8.312 | 8.312 | 8.312 | 8.312 | 8.312 | 8.312 would require\n         \u2514\u2500 python >=3.9,<3.10.0a0, for which no candidates were found.\n</pre><pre>osx_64_numpy1.22python3.10.____cpython: Cannot solve the request because of: root_base 6.32.8.* cannot be installed because there are no viable options:\n\u2514\u2500 root_base 6.32.8 | 6.32.8 | 6.32.8 | 6.32.8 | 6.32.8 would require\n   \u2514\u2500 pythia8 >=8.312,<8.400.0a0, which cannot be installed because there are no viable options:\n      \u251C\u2500 pythia8 8.312 | 8.312 | 8.312 would require\n      \u2502  \u2514\u2500 _x86_64-microarch-level >=3, which cannot be installed because there are no viable options:\n      \u2502     \u2514\u2500 _x86_64-microarch-level 3 | 3 | 3 | 3 | 3 | 3 | 3 | 3 | 3 | 3 | 3 | 3 | 3 | 3 | 3 | 3 | 3 | 3 | 3 | 3 | 3 | 3 | 3 | 3 | 3 | 3 | 3 | 3 | 3 | 3 | 4 | 4 | 4 | 4 | 4 | 4 | 4 | 4 | 4 | 4 | 4 | 4 | 4 | 4 | 4 | 4 | 4 | 4 would require\n      \u2502        \u2514\u2500 __archspec ==1 cannonlake, for which no candidates were found.\n      \u251C\u2500 pythia8 8.312 | 8.312 | 8.312 would require\n      \u2502  \u2514\u2500 _x86_64-microarch-level >=1, which cannot be installed because there are no viable options:\n      \u2502     \u2514\u2500 _x86_64-microarch-level 1 | 1 | 1 | 1 | 1 | 1 | 1 | 1 | 1 | 1 | 1 | 1 | 2 | 2 | 2 | 2 | 2 | 2 | 2 | 2 | 2 | 2 | 2 | 2 | 2 | 2 | 2 | 2 | 2 | 2 | 2 | 2 | 2 | 2 | 2 | 2 would require\n      \u2502        \u2514\u2500 __archspec ==1 core2, for which no candidates were found.\n      \u2514\u2500 pythia8 8.312 | 8.312 | 8.312 | 8.312 | 8.312 | 8.312 | 8.312 | 8.312 | 8.312 | 8.312 | 8.312 | 8.312 | 8.312 | 8.312 | 8.312 | 8.312 | 8.312 | 8.312 | 8.312 | 8.312 | 8.312 | 8.312 | 8.312 | 8.312 would require\n         \u2514\u2500 python >=3.9,<3.10.0a0, for which no candidates were found.\n</pre><pre>osx_64_numpy1.22python3.9.____cpython: Cannot solve the request because of: root_base 6.32.8.* cannot be installed because there are no viable options:\n\u2514\u2500 root_base 6.32.8 | 6.32.8 | 6.32.8 | 6.32.8 | 6.32.8 would require\n   \u2514\u2500 pythia8 >=8.312,<8.400.0a0, which cannot be installed because there are no viable options:\n      \u251C\u2500 pythia8 8.312 | 8.312 | 8.312 would require\n      \u2502  \u2514\u2500 _x86_64-microarch-level >=3, which cannot be installed because there are no viable options:\n      \u2502     \u2514\u2500 _x86_64-microarch-level 3 | 3 | 3 | 3 | 3 | 3 | 3 | 3 | 3 | 3 | 3 | 3 | 3 | 3 | 3 | 3 | 3 | 3 | 3 | 3 | 3 | 3 | 3 | 3 | 3 | 3 | 3 | 3 | 3 | 3 | 4 | 4 | 4 | 4 | 4 | 4 | 4 | 4 | 4 | 4 | 4 | 4 | 4 | 4 | 4 | 4 | 4 | 4 would require\n      \u2502        \u2514\u2500 __archspec ==1 cannonlake, for which no candidates were found.\n      \u251C\u2500 pythia8 8.312 | 8.312 | 8.312 would require\n      \u2502  \u2514\u2500 _x86_64-microarch-level >=1, which cannot be installed because there are no viable options:\n      \u2502     \u2514\u2500 _x86_64-microarch-level 1 | 1 | 1 | 1 | 1 | 1 | 1 | 1 | 1 | 1 | 1 | 1 | 2 | 2 | 2 | 2 | 2 | 2 | 2 | 2 | 2 | 2 | 2 | 2 | 2 | 2 | 2 | 2 | 2 | 2 | 2 | 2 | 2 | 2 | 2 | 2 would require\n      \u2502        \u2514\u2500 __archspec ==1 core2, for which no candidates were found.\n      \u2514\u2500 pythia8 8.312 | 8.312 | 8.312 | 8.312 | 8.312 | 8.312 | 8.312 | 8.312 | 8.312 | 8.312 | 8.312 | 8.312 | 8.312 | 8.312 | 8.312 | 8.312 | 8.312 | 8.312 | 8.312 | 8.312 | 8.312 | 8.312 | 8.312 | 8.312 would require\n         \u2514\u2500 python >=3.10,<3.11.0a0, for which no candidates were found.\n</pre><pre>osx_64_numpy1.23python3.11.____cpython: Cannot solve the request because of: root_base 6.32.8.* cannot be installed because there are no viable options:\n\u2514\u2500 root_base 6.32.8 | 6.32.8 | 6.32.8 | 6.32.8 | 6.32.8 would require\n   \u2514\u2500 pythia8 >=8.312,<8.400.0a0, which cannot be installed because there are no viable options:\n      \u251C\u2500 pythia8 8.312 | 8.312 | 8.312 would require\n      \u2502  \u2514\u2500 _x86_64-microarch-level >=3, which cannot be installed because there are no viable options:\n      \u2502     \u2514\u2500 _x86_64-microarch-level 3 | 3 | 3 | 3 | 3 | 3 | 3 | 3 | 3 | 3 | 3 | 3 | 3 | 3 | 3 | 3 | 3 | 3 | 3 | 3 | 3 | 3 | 3 | 3 | 3 | 3 | 3 | 3 | 3 | 3 | 4 | 4 | 4 | 4 | 4 | 4 | 4 | 4 | 4 | 4 | 4 | 4 | 4 | 4 | 4 | 4 | 4 | 4 would require\n      \u2502        \u2514\u2500 __archspec ==1 cannonlake, for which no candidates were found.\n      \u251C\u2500 pythia8 8.312 | 8.312 | 8.312 would require\n      \u2502  \u2514\u2500 _x86_64-microarch-level >=1, which cannot be installed because there are no viable options:\n      \u2502     \u2514\u2500 _x86_64-microarch-level 1 | 1 | 1 | 1 | 1 | 1 | 1 | 1 | 1 | 1 | 1 | 1 | 2 | 2 | 2 | 2 | 2 | 2 | 2 | 2 | 2 | 2 | 2 | 2 | 2 | 2 | 2 | 2 | 2 | 2 | 2 | 2 | 2 | 2 | 2 | 2 would require\n      \u2502        \u2514\u2500 __archspec ==1 core2, for which no candidates were found.\n      \u2514\u2500 pythia8 8.312 | 8.312 | 8.312 | 8.312 | 8.312 | 8.312 | 8.312 | 8.312 | 8.312 | 8.312 | 8.312 | 8.312 | 8.312 | 8.312 | 8.312 | 8.312 | 8.312 | 8.312 | 8.312 | 8.312 | 8.312 | 8.312 | 8.312 | 8.312 would require\n         \u2514\u2500 python >=3.9,<3.10.0a0, for which no candidates were found.\n</pre><pre>osx_64_numpy1.26python3.12.____cpython: Cannot solve the request because of: root_base 6.32.8.* cannot be installed because there are no viable options:\n\u2514\u2500 root_base 6.32.8 | 6.32.8 | 6.32.8 | 6.32.8 | 6.32.8 would require\n   \u2514\u2500 pythia8 >=8.312,<8.400.0a0, which cannot be installed because there are no viable options:\n      \u251C\u2500 pythia8 8.312 | 8.312 | 8.312 would require\n      \u2502  \u2514\u2500 _x86_64-microarch-level >=3, which cannot be installed because there are no viable options:\n      \u2502     \u2514\u2500 _x86_64-microarch-level 3 | 3 | 3 | 3 | 3 | 3 | 3 | 3 | 3 | 3 | 3 | 3 | 3 | 3 | 3 | 3 | 3 | 3 | 3 | 3 | 3 | 3 | 3 | 3 | 3 | 3 | 3 | 3 | 3 | 3 | 4 | 4 | 4 | 4 | 4 | 4 | 4 | 4 | 4 | 4 | 4 | 4 | 4 | 4 | 4 | 4 | 4 | 4 would require\n      \u2502        \u2514\u2500 __archspec ==1 cannonlake, for which no candidates were found.\n      \u251C\u2500 pythia8 8.312 | 8.312 | 8.312 would require\n      \u2502  \u2514\u2500 _x86_64-microarch-level >=1, which cannot be installed because there are no viable options:\n      \u2502     \u2514\u2500 _x86_64-microarch-level 1 | 1 | 1 | 1 | 1 | 1 | 1 | 1 | 1 | 1 | 1 | 1 | 2 | 2 | 2 | 2 | 2 | 2 | 2 | 2 | 2 | 2 | 2 | 2 | 2 | 2 | 2 | 2 | 2 | 2 | 2 | 2 | 2 | 2 | 2 | 2 would require\n      \u2502        \u2514\u2500 __archspec ==1 core2, for which no candidates were found.\n      \u2514\u2500 pythia8 8.312 | 8.312 | 8.312 | 8.312 | 8.312 | 8.312 | 8.312 | 8.312 | 8.312 | 8.312 | 8.312 | 8.312 | 8.312 | 8.312 | 8.312 | 8.312 | 8.312 | 8.312 | 8.312 | 8.312 | 8.312 | 8.312 | 8.312 | 8.312 would require\n         \u2514\u2500 python >=3.9,<3.10.0a0, for which no candidates were found.\n\n        </pre>\n        </div>\n        </details>"
    },
    "lhcb-simpletools": {
      "immediate_children": [],
      "num_descendants": 0,
      "pre_pr_migrator_status": "not solvable (<a href='https://github.com/regro/cf-scripts/actions/runs/13200643317'>bot CI job</a>) @ main\n        <details>\n        <div align=\"left\">\n        <pre>\n        linux_64_: Cannot solve the request because of: root_base 6.32.8.* cannot be installed because there are no viable options:\n\u2514\u2500 root_base 6.32.8 | 6.32.8 | 6.32.8 | 6.32.8 | 6.32.8 would require\n   \u2514\u2500 pythia8 >=8.312,<8.400.0a0, which cannot be installed because there are no viable options:\n      \u251C\u2500 pythia8 8.312 | 8.312 | 8.312 | 8.312 | 8.312 | 8.312 | 8.312 | 8.312 | 8.312 | 8.312 | 8.312 | 8.312 | 8.312 | 8.312 | 8.312 would require\n      \u2502  \u2514\u2500 _x86_64-microarch-level >=3, which cannot be installed because there are no viable options:\n      \u2502     \u2514\u2500 _x86_64-microarch-level 3 | 3 | 3 | 3 | 3 | 3 | 3 | 3 | 3 | 3 | 3 | 3 | 3 | 3 | 3 | 3 | 3 | 3 | 3 | 3 | 3 | 3 | 3 | 3 | 3 | 3 | 3 | 3 | 3 | 3 | 4 | 4 | 4 | 4 | 4 | 4 | 4 | 4 | 4 | 4 | 4 | 4 | 4 | 4 | 4 | 4 | 4 | 4 would require\n      \u2502        \u2514\u2500 __archspec ==1 cannonlake, for which no candidates were found.\n      \u2514\u2500 pythia8 8.312 | 8.312 | 8.312 | 8.312 | 8.312 | 8.312 | 8.312 | 8.312 | 8.312 | 8.312 | 8.312 | 8.312 | 8.312 | 8.312 | 8.312 would require\n         \u2514\u2500 _x86_64-microarch-level >=1, which cannot be installed because there are no viable options:\n            \u2514\u2500 _x86_64-microarch-level 1 | 1 | 1 | 1 | 1 | 1 | 1 | 1 | 1 | 1 | 1 | 1 | 2 | 2 | 2 | 2 | 2 | 2 | 2 | 2 | 2 | 2 | 2 | 2 | 2 | 2 | 2 | 2 | 2 | 2 | 2 | 2 | 2 | 2 | 2 | 2 would require\n               \u2514\u2500 __archspec ==1 core2, for which no candidates were found.\n</pre><pre>osx_64_: Cannot solve the request because of: root_base 6.32.8.* cannot be installed because there are no viable options:\n\u2514\u2500 root_base 6.32.8 | 6.32.8 | 6.32.8 | 6.32.8 | 6.32.8 would require\n   \u2514\u2500 pythia8 >=8.312,<8.400.0a0, which cannot be installed because there are no viable options:\n      \u251C\u2500 pythia8 8.312 | 8.312 | 8.312 | 8.312 | 8.312 | 8.312 | 8.312 | 8.312 | 8.312 | 8.312 | 8.312 | 8.312 | 8.312 | 8.312 | 8.312 would require\n      \u2502  \u2514\u2500 _x86_64-microarch-level >=3, which cannot be installed because there are no viable options:\n      \u2502     \u2514\u2500 _x86_64-microarch-level 3 | 3 | 3 | 3 | 3 | 3 | 3 | 3 | 3 | 3 | 3 | 3 | 3 | 3 | 3 | 3 | 3 | 3 | 3 | 3 | 3 | 3 | 3 | 3 | 3 | 3 | 3 | 3 | 3 | 3 | 4 | 4 | 4 | 4 | 4 | 4 | 4 | 4 | 4 | 4 | 4 | 4 | 4 | 4 | 4 | 4 | 4 | 4 would require\n      \u2502        \u2514\u2500 __archspec ==1 cannonlake, for which no candidates were found.\n      \u2514\u2500 pythia8 8.312 | 8.312 | 8.312 | 8.312 | 8.312 | 8.312 | 8.312 | 8.312 | 8.312 | 8.312 | 8.312 | 8.312 | 8.312 | 8.312 | 8.312 would require\n         \u2514\u2500 _x86_64-microarch-level >=1, which cannot be installed because there are no viable options:\n            \u2514\u2500 _x86_64-microarch-level 1 | 1 | 1 | 1 | 1 | 1 | 1 | 1 | 1 | 1 | 1 | 1 | 2 | 2 | 2 | 2 | 2 | 2 | 2 | 2 | 2 | 2 | 2 | 2 | 2 | 2 | 2 | 2 | 2 | 2 | 2 | 2 | 2 | 2 | 2 | 2 would require\n               \u2514\u2500 __archspec ==1 core2, for which no candidates were found.\n\n        </pre>\n        </div>\n        </details>"
    },
    "omicron": {
      "immediate_children": [
        "upv",
        "vetoperf"
      ],
      "num_descendants": 2,
      "pre_pr_migrator_status": ""
    },
    "ostaphep": {
      "immediate_children": [],
      "num_descendants": 0,
      "pre_pr_migrator_status": "not solvable (<a href='https://github.com/regro/cf-scripts/actions/runs/13202547225'>bot CI job</a>) @ main\n        <details>\n        <div align=\"left\">\n        <pre>\n        linux_64_python3.10.____cpython: Cannot solve the request because of: root_base 6.32.8.* cannot be installed because there are no viable options:\n\u2514\u2500 root_base 6.32.8 | 6.32.8 | 6.32.8 | 6.32.8 | 6.32.8 would require\n   \u2514\u2500 pythia8 >=8.312,<8.400.0a0, which cannot be installed because there are no viable options:\n      \u251C\u2500 pythia8 8.312 | 8.312 | 8.312 would require\n      \u2502  \u2514\u2500 _x86_64-microarch-level >=3, which cannot be installed because there are no viable options:\n      \u2502     \u2514\u2500 _x86_64-microarch-level 3 | 3 | 3 | 3 | 3 | 3 | 3 | 3 | 3 | 3 | 3 | 3 | 3 | 3 | 3 | 3 | 3 | 3 | 3 | 3 | 3 | 3 | 3 | 3 | 3 | 3 | 3 | 3 | 3 | 3 | 4 | 4 | 4 | 4 | 4 | 4 | 4 | 4 | 4 | 4 | 4 | 4 | 4 | 4 | 4 | 4 | 4 | 4 would require\n      \u2502        \u2514\u2500 __archspec ==1 cannonlake, for which no candidates were found.\n      \u251C\u2500 pythia8 8.312 | 8.312 | 8.312 would require\n      \u2502  \u2514\u2500 _x86_64-microarch-level >=1, which cannot be installed because there are no viable options:\n      \u2502     \u2514\u2500 _x86_64-microarch-level 1 | 1 | 1 | 1 | 1 | 1 | 1 | 1 | 1 | 1 | 1 | 1 | 2 | 2 | 2 | 2 | 2 | 2 | 2 | 2 | 2 | 2 | 2 | 2 | 2 | 2 | 2 | 2 | 2 | 2 | 2 | 2 | 2 | 2 | 2 | 2 would require\n      \u2502        \u2514\u2500 __archspec ==1 core2, for which no candidates were found.\n      \u2514\u2500 pythia8 8.312 | 8.312 | 8.312 | 8.312 | 8.312 | 8.312 | 8.312 | 8.312 | 8.312 | 8.312 | 8.312 | 8.312 | 8.312 | 8.312 | 8.312 | 8.312 | 8.312 | 8.312 | 8.312 | 8.312 | 8.312 | 8.312 | 8.312 | 8.312 would require\n         \u2514\u2500 python >=3.9,<3.10.0a0, for which no candidates were found.\n</pre><pre>linux_64_python3.11.____cpython: Cannot solve the request because of: root_base 6.32.8.* cannot be installed because there are no viable options:\n\u2514\u2500 root_base 6.32.8 | 6.32.8 | 6.32.8 | 6.32.8 | 6.32.8 would require\n   \u2514\u2500 pythia8 >=8.312,<8.400.0a0, which cannot be installed because there are no viable options:\n      \u251C\u2500 pythia8 8.312 | 8.312 | 8.312 would require\n      \u2502  \u2514\u2500 _x86_64-microarch-level >=3, which cannot be installed because there are no viable options:\n      \u2502     \u2514\u2500 _x86_64-microarch-level 3 | 3 | 3 | 3 | 3 | 3 | 3 | 3 | 3 | 3 | 3 | 3 | 3 | 3 | 3 | 3 | 3 | 3 | 3 | 3 | 3 | 3 | 3 | 3 | 3 | 3 | 3 | 3 | 3 | 3 | 4 | 4 | 4 | 4 | 4 | 4 | 4 | 4 | 4 | 4 | 4 | 4 | 4 | 4 | 4 | 4 | 4 | 4 would require\n      \u2502        \u2514\u2500 __archspec ==1 cannonlake, for which no candidates were found.\n      \u251C\u2500 pythia8 8.312 | 8.312 | 8.312 would require\n      \u2502  \u2514\u2500 _x86_64-microarch-level >=1, which cannot be installed because there are no viable options:\n      \u2502     \u2514\u2500 _x86_64-microarch-level 1 | 1 | 1 | 1 | 1 | 1 | 1 | 1 | 1 | 1 | 1 | 1 | 2 | 2 | 2 | 2 | 2 | 2 | 2 | 2 | 2 | 2 | 2 | 2 | 2 | 2 | 2 | 2 | 2 | 2 | 2 | 2 | 2 | 2 | 2 | 2 would require\n      \u2502        \u2514\u2500 __archspec ==1 core2, for which no candidates were found.\n      \u2514\u2500 pythia8 8.312 | 8.312 | 8.312 | 8.312 | 8.312 | 8.312 | 8.312 | 8.312 | 8.312 | 8.312 | 8.312 | 8.312 | 8.312 | 8.312 | 8.312 | 8.312 | 8.312 | 8.312 | 8.312 | 8.312 | 8.312 | 8.312 | 8.312 | 8.312 would require\n         \u2514\u2500 python >=3.9,<3.10.0a0, for which no candidates were found.\n</pre><pre>linux_64_python3.12.____cpython: Cannot solve the request because of: root_base 6.32.8.* cannot be installed because there are no viable options:\n\u2514\u2500 root_base 6.32.8 | 6.32.8 | 6.32.8 | 6.32.8 | 6.32.8 would require\n   \u2514\u2500 pythia8 >=8.312,<8.400.0a0, which cannot be installed because there are no viable options:\n      \u251C\u2500 pythia8 8.312 | 8.312 | 8.312 would require\n      \u2502  \u2514\u2500 _x86_64-microarch-level >=3, which cannot be installed because there are no viable options:\n      \u2502     \u2514\u2500 _x86_64-microarch-level 3 | 3 | 3 | 3 | 3 | 3 | 3 | 3 | 3 | 3 | 3 | 3 | 3 | 3 | 3 | 3 | 3 | 3 | 3 | 3 | 3 | 3 | 3 | 3 | 3 | 3 | 3 | 3 | 3 | 3 | 4 | 4 | 4 | 4 | 4 | 4 | 4 | 4 | 4 | 4 | 4 | 4 | 4 | 4 | 4 | 4 | 4 | 4 would require\n      \u2502        \u2514\u2500 __archspec ==1 cannonlake, for which no candidates were found.\n      \u251C\u2500 pythia8 8.312 | 8.312 | 8.312 would require\n      \u2502  \u2514\u2500 _x86_64-microarch-level >=1, which cannot be installed because there are no viable options:\n      \u2502     \u2514\u2500 _x86_64-microarch-level 1 | 1 | 1 | 1 | 1 | 1 | 1 | 1 | 1 | 1 | 1 | 1 | 2 | 2 | 2 | 2 | 2 | 2 | 2 | 2 | 2 | 2 | 2 | 2 | 2 | 2 | 2 | 2 | 2 | 2 | 2 | 2 | 2 | 2 | 2 | 2 would require\n      \u2502        \u2514\u2500 __archspec ==1 core2, for which no candidates were found.\n      \u2514\u2500 pythia8 8.312 | 8.312 | 8.312 | 8.312 | 8.312 | 8.312 | 8.312 | 8.312 | 8.312 | 8.312 | 8.312 | 8.312 | 8.312 | 8.312 | 8.312 | 8.312 | 8.312 | 8.312 | 8.312 | 8.312 | 8.312 | 8.312 | 8.312 | 8.312 would require\n         \u2514\u2500 python >=3.9,<3.10.0a0, for which no candidates were found.\n</pre><pre>linux_64_python3.9.____cpython: Cannot solve the request because of: root_base 6.32.8.* cannot be installed because there are no viable options:\n\u2514\u2500 root_base 6.32.8 | 6.32.8 | 6.32.8 | 6.32.8 | 6.32.8 would require\n   \u2514\u2500 pythia8 >=8.312,<8.400.0a0, which cannot be installed because there are no viable options:\n      \u251C\u2500 pythia8 8.312 | 8.312 | 8.312 would require\n      \u2502  \u2514\u2500 _x86_64-microarch-level >=3, which cannot be installed because there are no viable options:\n      \u2502     \u2514\u2500 _x86_64-microarch-level 3 | 3 | 3 | 3 | 3 | 3 | 3 | 3 | 3 | 3 | 3 | 3 | 3 | 3 | 3 | 3 | 3 | 3 | 3 | 3 | 3 | 3 | 3 | 3 | 3 | 3 | 3 | 3 | 3 | 3 | 4 | 4 | 4 | 4 | 4 | 4 | 4 | 4 | 4 | 4 | 4 | 4 | 4 | 4 | 4 | 4 | 4 | 4 would require\n      \u2502        \u2514\u2500 __archspec ==1 cannonlake, for which no candidates were found.\n      \u251C\u2500 pythia8 8.312 | 8.312 | 8.312 would require\n      \u2502  \u2514\u2500 _x86_64-microarch-level >=1, which cannot be installed because there are no viable options:\n      \u2502     \u2514\u2500 _x86_64-microarch-level 1 | 1 | 1 | 1 | 1 | 1 | 1 | 1 | 1 | 1 | 1 | 1 | 2 | 2 | 2 | 2 | 2 | 2 | 2 | 2 | 2 | 2 | 2 | 2 | 2 | 2 | 2 | 2 | 2 | 2 | 2 | 2 | 2 | 2 | 2 | 2 would require\n      \u2502        \u2514\u2500 __archspec ==1 core2, for which no candidates were found.\n      \u2514\u2500 pythia8 8.312 | 8.312 | 8.312 | 8.312 | 8.312 | 8.312 | 8.312 | 8.312 | 8.312 | 8.312 | 8.312 | 8.312 | 8.312 | 8.312 | 8.312 | 8.312 | 8.312 | 8.312 | 8.312 | 8.312 | 8.312 | 8.312 | 8.312 | 8.312 would require\n         \u2514\u2500 python >=3.10,<3.11.0a0, for which no candidates were found.\n\n        </pre>\n        </div>\n        </details>"
    },
    "rapidsim": {
      "immediate_children": [],
      "num_descendants": 0,
      "pre_pr_migrator_status": "not solvable (<a href='https://github.com/regro/cf-scripts/actions/runs/13202547225'>bot CI job</a>) @ main\n        <details>\n        <div align=\"left\">\n        <pre>\n        linux_64_: Cannot solve the request because of: root_base 6.32.8.* cannot be installed because there are no viable options:\n\u2514\u2500 root_base 6.32.8 | 6.32.8 | 6.32.8 | 6.32.8 | 6.32.8 would require\n   \u2514\u2500 pythia8 >=8.312,<8.400.0a0, which cannot be installed because there are no viable options:\n      \u251C\u2500 pythia8 8.312 | 8.312 | 8.312 | 8.312 | 8.312 | 8.312 | 8.312 | 8.312 | 8.312 | 8.312 | 8.312 | 8.312 | 8.312 | 8.312 | 8.312 would require\n      \u2502  \u2514\u2500 _x86_64-microarch-level >=3, which cannot be installed because there are no viable options:\n      \u2502     \u2514\u2500 _x86_64-microarch-level 3 | 3 | 3 | 3 | 3 | 3 | 3 | 3 | 3 | 3 | 3 | 3 | 3 | 3 | 3 | 3 | 3 | 3 | 3 | 3 | 3 | 3 | 3 | 3 | 3 | 3 | 3 | 3 | 3 | 3 | 4 | 4 | 4 | 4 | 4 | 4 | 4 | 4 | 4 | 4 | 4 | 4 | 4 | 4 | 4 | 4 | 4 | 4 would require\n      \u2502        \u2514\u2500 __archspec ==1 cannonlake, for which no candidates were found.\n      \u2514\u2500 pythia8 8.312 | 8.312 | 8.312 | 8.312 | 8.312 | 8.312 | 8.312 | 8.312 | 8.312 | 8.312 | 8.312 | 8.312 | 8.312 | 8.312 | 8.312 would require\n         \u2514\u2500 _x86_64-microarch-level >=1, which cannot be installed because there are no viable options:\n            \u2514\u2500 _x86_64-microarch-level 1 | 1 | 1 | 1 | 1 | 1 | 1 | 1 | 1 | 1 | 1 | 1 | 2 | 2 | 2 | 2 | 2 | 2 | 2 | 2 | 2 | 2 | 2 | 2 | 2 | 2 | 2 | 2 | 2 | 2 | 2 | 2 | 2 | 2 | 2 | 2 would require\n               \u2514\u2500 __archspec ==1 core2, for which no candidates were found.\n</pre><pre>osx_64_: Cannot solve the request because of: root_base 6.32.8.* cannot be installed because there are no viable options:\n\u2514\u2500 root_base 6.32.8 | 6.32.8 | 6.32.8 | 6.32.8 | 6.32.8 would require\n   \u2514\u2500 pythia8 >=8.312,<8.400.0a0, which cannot be installed because there are no viable options:\n      \u251C\u2500 pythia8 8.312 | 8.312 | 8.312 | 8.312 | 8.312 | 8.312 | 8.312 | 8.312 | 8.312 | 8.312 | 8.312 | 8.312 | 8.312 | 8.312 | 8.312 would require\n      \u2502  \u2514\u2500 _x86_64-microarch-level >=3, which cannot be installed because there are no viable options:\n      \u2502     \u2514\u2500 _x86_64-microarch-level 3 | 3 | 3 | 3 | 3 | 3 | 3 | 3 | 3 | 3 | 3 | 3 | 3 | 3 | 3 | 3 | 3 | 3 | 3 | 3 | 3 | 3 | 3 | 3 | 3 | 3 | 3 | 3 | 3 | 3 | 4 | 4 | 4 | 4 | 4 | 4 | 4 | 4 | 4 | 4 | 4 | 4 | 4 | 4 | 4 | 4 | 4 | 4 would require\n      \u2502        \u2514\u2500 __archspec ==1 cannonlake, for which no candidates were found.\n      \u2514\u2500 pythia8 8.312 | 8.312 | 8.312 | 8.312 | 8.312 | 8.312 | 8.312 | 8.312 | 8.312 | 8.312 | 8.312 | 8.312 | 8.312 | 8.312 | 8.312 would require\n         \u2514\u2500 _x86_64-microarch-level >=1, which cannot be installed because there are no viable options:\n            \u2514\u2500 _x86_64-microarch-level 1 | 1 | 1 | 1 | 1 | 1 | 1 | 1 | 1 | 1 | 1 | 1 | 2 | 2 | 2 | 2 | 2 | 2 | 2 | 2 | 2 | 2 | 2 | 2 | 2 | 2 | 2 | 2 | 2 | 2 | 2 | 2 | 2 | 2 | 2 | 2 would require\n               \u2514\u2500 __archspec ==1 core2, for which no candidates were found.\n\n        </pre>\n        </div>\n        </details>"
    },
    "stir": {
      "immediate_children": [],
      "num_descendants": 0,
      "pr_status": "unknown",
      "pr_url": "https://github.com/conda-forge/stir-feedstock/pull/128",
      "pre_pr_migrator_status": ""
    },
    "upv": {
      "immediate_children": [],
      "num_descendants": 0,
      "pre_pr_migrator_status": ""
    },
    "vetoperf": {
      "immediate_children": [
        "upv"
      ],
      "num_descendants": 1,
      "pre_pr_migrator_status": ""
    },
    "yoda": {
      "immediate_children": [],
      "num_descendants": 0,
      "pre_pr_migrator_status": "not solvable (<a href='https://github.com/regro/cf-scripts/actions/runs/13200179834'>bot CI job</a>) @ main\n        <details>\n        <div align=\"left\">\n        <pre>\n        linux_64_python3.10.____cpython: Cannot solve the request because of: root_base 6.32.8.* cannot be installed because there are no viable options:\n\u2514\u2500 root_base 6.32.8 | 6.32.8 | 6.32.8 | 6.32.8 | 6.32.8 would require\n   \u2514\u2500 pythia8 >=8.312,<8.400.0a0, which cannot be installed because there are no viable options:\n      \u251C\u2500 pythia8 8.312 | 8.312 | 8.312 would require\n      \u2502  \u2514\u2500 _x86_64-microarch-level >=3, which cannot be installed because there are no viable options:\n      \u2502     \u2514\u2500 _x86_64-microarch-level 3 | 3 | 3 | 3 | 3 | 3 | 3 | 3 | 3 | 3 | 3 | 3 | 3 | 3 | 3 | 3 | 3 | 3 | 3 | 3 | 3 | 3 | 3 | 3 | 3 | 3 | 3 | 3 | 3 | 3 | 4 | 4 | 4 | 4 | 4 | 4 | 4 | 4 | 4 | 4 | 4 | 4 | 4 | 4 | 4 | 4 | 4 | 4 would require\n      \u2502        \u2514\u2500 __archspec ==1 cannonlake, for which no candidates were found.\n      \u251C\u2500 pythia8 8.312 | 8.312 | 8.312 would require\n      \u2502  \u2514\u2500 _x86_64-microarch-level >=1, which cannot be installed because there are no viable options:\n      \u2502     \u2514\u2500 _x86_64-microarch-level 1 | 1 | 1 | 1 | 1 | 1 | 1 | 1 | 1 | 1 | 1 | 1 | 2 | 2 | 2 | 2 | 2 | 2 | 2 | 2 | 2 | 2 | 2 | 2 | 2 | 2 | 2 | 2 | 2 | 2 | 2 | 2 | 2 | 2 | 2 | 2 would require\n      \u2502        \u2514\u2500 __archspec ==1 core2, for which no candidates were found.\n      \u2514\u2500 pythia8 8.312 | 8.312 | 8.312 | 8.312 | 8.312 | 8.312 | 8.312 | 8.312 | 8.312 | 8.312 | 8.312 | 8.312 | 8.312 | 8.312 | 8.312 | 8.312 | 8.312 | 8.312 | 8.312 | 8.312 | 8.312 | 8.312 | 8.312 | 8.312 would require\n         \u2514\u2500 python >=3.9,<3.10.0a0, for which no candidates were found.\n</pre><pre>linux_64_python3.11.____cpython: Cannot solve the request because of: root_base 6.32.8.* cannot be installed because there are no viable options:\n\u2514\u2500 root_base 6.32.8 | 6.32.8 | 6.32.8 | 6.32.8 | 6.32.8 would require\n   \u2514\u2500 pythia8 >=8.312,<8.400.0a0, which cannot be installed because there are no viable options:\n      \u251C\u2500 pythia8 8.312 | 8.312 | 8.312 would require\n      \u2502  \u2514\u2500 _x86_64-microarch-level >=3, which cannot be installed because there are no viable options:\n      \u2502     \u2514\u2500 _x86_64-microarch-level 3 | 3 | 3 | 3 | 3 | 3 | 3 | 3 | 3 | 3 | 3 | 3 | 3 | 3 | 3 | 3 | 3 | 3 | 3 | 3 | 3 | 3 | 3 | 3 | 3 | 3 | 3 | 3 | 3 | 3 | 4 | 4 | 4 | 4 | 4 | 4 | 4 | 4 | 4 | 4 | 4 | 4 | 4 | 4 | 4 | 4 | 4 | 4 would require\n      \u2502        \u2514\u2500 __archspec ==1 cannonlake, for which no candidates were found.\n      \u251C\u2500 pythia8 8.312 | 8.312 | 8.312 would require\n      \u2502  \u2514\u2500 _x86_64-microarch-level >=1, which cannot be installed because there are no viable options:\n      \u2502     \u2514\u2500 _x86_64-microarch-level 1 | 1 | 1 | 1 | 1 | 1 | 1 | 1 | 1 | 1 | 1 | 1 | 2 | 2 | 2 | 2 | 2 | 2 | 2 | 2 | 2 | 2 | 2 | 2 | 2 | 2 | 2 | 2 | 2 | 2 | 2 | 2 | 2 | 2 | 2 | 2 would require\n      \u2502        \u2514\u2500 __archspec ==1 core2, for which no candidates were found.\n      \u2514\u2500 pythia8 8.312 | 8.312 | 8.312 | 8.312 | 8.312 | 8.312 | 8.312 | 8.312 | 8.312 | 8.312 | 8.312 | 8.312 | 8.312 | 8.312 | 8.312 | 8.312 | 8.312 | 8.312 | 8.312 | 8.312 | 8.312 | 8.312 | 8.312 | 8.312 would require\n         \u2514\u2500 python >=3.9,<3.10.0a0, for which no candidates were found.\n</pre><pre>linux_64_python3.12.____cpython: Cannot solve the request because of: root_base 6.32.8.* cannot be installed because there are no viable options:\n\u2514\u2500 root_base 6.32.8 | 6.32.8 | 6.32.8 | 6.32.8 | 6.32.8 would require\n   \u2514\u2500 pythia8 >=8.312,<8.400.0a0, which cannot be installed because there are no viable options:\n      \u251C\u2500 pythia8 8.312 | 8.312 | 8.312 would require\n      \u2502  \u2514\u2500 _x86_64-microarch-level >=3, which cannot be installed because there are no viable options:\n      \u2502     \u2514\u2500 _x86_64-microarch-level 3 | 3 | 3 | 3 | 3 | 3 | 3 | 3 | 3 | 3 | 3 | 3 | 3 | 3 | 3 | 3 | 3 | 3 | 3 | 3 | 3 | 3 | 3 | 3 | 3 | 3 | 3 | 3 | 3 | 3 | 4 | 4 | 4 | 4 | 4 | 4 | 4 | 4 | 4 | 4 | 4 | 4 | 4 | 4 | 4 | 4 | 4 | 4 would require\n      \u2502        \u2514\u2500 __archspec ==1 cannonlake, for which no candidates were found.\n      \u251C\u2500 pythia8 8.312 | 8.312 | 8.312 would require\n      \u2502  \u2514\u2500 _x86_64-microarch-level >=1, which cannot be installed because there are no viable options:\n      \u2502     \u2514\u2500 _x86_64-microarch-level 1 | 1 | 1 | 1 | 1 | 1 | 1 | 1 | 1 | 1 | 1 | 1 | 2 | 2 | 2 | 2 | 2 | 2 | 2 | 2 | 2 | 2 | 2 | 2 | 2 | 2 | 2 | 2 | 2 | 2 | 2 | 2 | 2 | 2 | 2 | 2 would require\n      \u2502        \u2514\u2500 __archspec ==1 core2, for which no candidates were found.\n      \u2514\u2500 pythia8 8.312 | 8.312 | 8.312 | 8.312 | 8.312 | 8.312 | 8.312 | 8.312 | 8.312 | 8.312 | 8.312 | 8.312 | 8.312 | 8.312 | 8.312 | 8.312 | 8.312 | 8.312 | 8.312 | 8.312 | 8.312 | 8.312 | 8.312 | 8.312 would require\n         \u2514\u2500 python >=3.9,<3.10.0a0, for which no candidates were found.\n</pre><pre>linux_64_python3.9.____cpython: Cannot solve the request because of: root_base 6.32.8.* cannot be installed because there are no viable options:\n\u2514\u2500 root_base 6.32.8 | 6.32.8 | 6.32.8 | 6.32.8 | 6.32.8 would require\n   \u2514\u2500 pythia8 >=8.312,<8.400.0a0, which cannot be installed because there are no viable options:\n      \u251C\u2500 pythia8 8.312 | 8.312 | 8.312 would require\n      \u2502  \u2514\u2500 _x86_64-microarch-level >=3, which cannot be installed because there are no viable options:\n      \u2502     \u2514\u2500 _x86_64-microarch-level 3 | 3 | 3 | 3 | 3 | 3 | 3 | 3 | 3 | 3 | 3 | 3 | 3 | 3 | 3 | 3 | 3 | 3 | 3 | 3 | 3 | 3 | 3 | 3 | 3 | 3 | 3 | 3 | 3 | 3 | 4 | 4 | 4 | 4 | 4 | 4 | 4 | 4 | 4 | 4 | 4 | 4 | 4 | 4 | 4 | 4 | 4 | 4 would require\n      \u2502        \u2514\u2500 __archspec ==1 cannonlake, for which no candidates were found.\n      \u251C\u2500 pythia8 8.312 | 8.312 | 8.312 would require\n      \u2502  \u2514\u2500 _x86_64-microarch-level >=1, which cannot be installed because there are no viable options:\n      \u2502     \u2514\u2500 _x86_64-microarch-level 1 | 1 | 1 | 1 | 1 | 1 | 1 | 1 | 1 | 1 | 1 | 1 | 2 | 2 | 2 | 2 | 2 | 2 | 2 | 2 | 2 | 2 | 2 | 2 | 2 | 2 | 2 | 2 | 2 | 2 | 2 | 2 | 2 | 2 | 2 | 2 would require\n      \u2502        \u2514\u2500 __archspec ==1 core2, for which no candidates were found.\n      \u2514\u2500 pythia8 8.312 | 8.312 | 8.312 | 8.312 | 8.312 | 8.312 | 8.312 | 8.312 | 8.312 | 8.312 | 8.312 | 8.312 | 8.312 | 8.312 | 8.312 | 8.312 | 8.312 | 8.312 | 8.312 | 8.312 | 8.312 | 8.312 | 8.312 | 8.312 would require\n         \u2514\u2500 python >=3.10,<3.11.0a0, for which no candidates were found.\n</pre><pre>osx_64_python3.10.____cpython: Cannot solve the request because of: root_base 6.32.8.* cannot be installed because there are no viable options:\n\u2514\u2500 root_base 6.32.8 | 6.32.8 | 6.32.8 | 6.32.8 | 6.32.8 would require\n   \u2514\u2500 pythia8 >=8.312,<8.400.0a0, which cannot be installed because there are no viable options:\n      \u251C\u2500 pythia8 8.312 | 8.312 | 8.312 would require\n      \u2502  \u2514\u2500 _x86_64-microarch-level >=3, which cannot be installed because there are no viable options:\n      \u2502     \u2514\u2500 _x86_64-microarch-level 3 | 3 | 3 | 3 | 3 | 3 | 3 | 3 | 3 | 3 | 3 | 3 | 3 | 3 | 3 | 3 | 3 | 3 | 3 | 3 | 3 | 3 | 3 | 3 | 3 | 3 | 3 | 3 | 3 | 3 | 4 | 4 | 4 | 4 | 4 | 4 | 4 | 4 | 4 | 4 | 4 | 4 | 4 | 4 | 4 | 4 | 4 | 4 would require\n      \u2502        \u2514\u2500 __archspec ==1 cannonlake, for which no candidates were found.\n      \u251C\u2500 pythia8 8.312 | 8.312 | 8.312 would require\n      \u2502  \u2514\u2500 _x86_64-microarch-level >=1, which cannot be installed because there are no viable options:\n      \u2502     \u2514\u2500 _x86_64-microarch-level 1 | 1 | 1 | 1 | 1 | 1 | 1 | 1 | 1 | 1 | 1 | 1 | 2 | 2 | 2 | 2 | 2 | 2 | 2 | 2 | 2 | 2 | 2 | 2 | 2 | 2 | 2 | 2 | 2 | 2 | 2 | 2 | 2 | 2 | 2 | 2 would require\n      \u2502        \u2514\u2500 __archspec ==1 core2, for which no candidates were found.\n      \u2514\u2500 pythia8 8.312 | 8.312 | 8.312 | 8.312 | 8.312 | 8.312 | 8.312 | 8.312 | 8.312 | 8.312 | 8.312 | 8.312 | 8.312 | 8.312 | 8.312 | 8.312 | 8.312 | 8.312 | 8.312 | 8.312 | 8.312 | 8.312 | 8.312 | 8.312 would require\n         \u2514\u2500 python >=3.9,<3.10.0a0, for which no candidates were found.\n</pre><pre>osx_64_python3.11.____cpython: Cannot solve the request because of: root_base 6.32.8.* cannot be installed because there are no viable options:\n\u2514\u2500 root_base 6.32.8 | 6.32.8 | 6.32.8 | 6.32.8 | 6.32.8 would require\n   \u2514\u2500 pythia8 >=8.312,<8.400.0a0, which cannot be installed because there are no viable options:\n      \u251C\u2500 pythia8 8.312 | 8.312 | 8.312 would require\n      \u2502  \u2514\u2500 _x86_64-microarch-level >=3, which cannot be installed because there are no viable options:\n      \u2502     \u2514\u2500 _x86_64-microarch-level 3 | 3 | 3 | 3 | 3 | 3 | 3 | 3 | 3 | 3 | 3 | 3 | 3 | 3 | 3 | 3 | 3 | 3 | 3 | 3 | 3 | 3 | 3 | 3 | 3 | 3 | 3 | 3 | 3 | 3 | 4 | 4 | 4 | 4 | 4 | 4 | 4 | 4 | 4 | 4 | 4 | 4 | 4 | 4 | 4 | 4 | 4 | 4 would require\n      \u2502        \u2514\u2500 __archspec ==1 cannonlake, for which no candidates were found.\n      \u251C\u2500 pythia8 8.312 | 8.312 | 8.312 would require\n      \u2502  \u2514\u2500 _x86_64-microarch-level >=1, which cannot be installed because there are no viable options:\n      \u2502     \u2514\u2500 _x86_64-microarch-level 1 | 1 | 1 | 1 | 1 | 1 | 1 | 1 | 1 | 1 | 1 | 1 | 2 | 2 | 2 | 2 | 2 | 2 | 2 | 2 | 2 | 2 | 2 | 2 | 2 | 2 | 2 | 2 | 2 | 2 | 2 | 2 | 2 | 2 | 2 | 2 would require\n      \u2502        \u2514\u2500 __archspec ==1 core2, for which no candidates were found.\n      \u2514\u2500 pythia8 8.312 | 8.312 | 8.312 | 8.312 | 8.312 | 8.312 | 8.312 | 8.312 | 8.312 | 8.312 | 8.312 | 8.312 | 8.312 | 8.312 | 8.312 | 8.312 | 8.312 | 8.312 | 8.312 | 8.312 | 8.312 | 8.312 | 8.312 | 8.312 would require\n         \u2514\u2500 python >=3.9,<3.10.0a0, for which no candidates were found.\n</pre><pre>osx_64_python3.12.____cpython: Cannot solve the request because of: root_base 6.32.8.* cannot be installed because there are no viable options:\n\u2514\u2500 root_base 6.32.8 | 6.32.8 | 6.32.8 | 6.32.8 | 6.32.8 would require\n   \u2514\u2500 pythia8 >=8.312,<8.400.0a0, which cannot be installed because there are no viable options:\n      \u251C\u2500 pythia8 8.312 | 8.312 | 8.312 would require\n      \u2502  \u2514\u2500 _x86_64-microarch-level >=3, which cannot be installed because there are no viable options:\n      \u2502     \u2514\u2500 _x86_64-microarch-level 3 | 3 | 3 | 3 | 3 | 3 | 3 | 3 | 3 | 3 | 3 | 3 | 3 | 3 | 3 | 3 | 3 | 3 | 3 | 3 | 3 | 3 | 3 | 3 | 3 | 3 | 3 | 3 | 3 | 3 | 4 | 4 | 4 | 4 | 4 | 4 | 4 | 4 | 4 | 4 | 4 | 4 | 4 | 4 | 4 | 4 | 4 | 4 would require\n      \u2502        \u2514\u2500 __archspec ==1 cannonlake, for which no candidates were found.\n      \u251C\u2500 pythia8 8.312 | 8.312 | 8.312 would require\n      \u2502  \u2514\u2500 _x86_64-microarch-level >=1, which cannot be installed because there are no viable options:\n      \u2502     \u2514\u2500 _x86_64-microarch-level 1 | 1 | 1 | 1 | 1 | 1 | 1 | 1 | 1 | 1 | 1 | 1 | 2 | 2 | 2 | 2 | 2 | 2 | 2 | 2 | 2 | 2 | 2 | 2 | 2 | 2 | 2 | 2 | 2 | 2 | 2 | 2 | 2 | 2 | 2 | 2 would require\n      \u2502        \u2514\u2500 __archspec ==1 core2, for which no candidates were found.\n      \u2514\u2500 pythia8 8.312 | 8.312 | 8.312 | 8.312 | 8.312 | 8.312 | 8.312 | 8.312 | 8.312 | 8.312 | 8.312 | 8.312 | 8.312 | 8.312 | 8.312 | 8.312 | 8.312 | 8.312 | 8.312 | 8.312 | 8.312 | 8.312 | 8.312 | 8.312 would require\n         \u2514\u2500 python >=3.9,<3.10.0a0, for which no candidates were found.\n</pre><pre>osx_64_python3.9.____cpython: Cannot solve the request because of: root_base 6.32.8.* cannot be installed because there are no viable options:\n\u2514\u2500 root_base 6.32.8 | 6.32.8 | 6.32.8 | 6.32.8 | 6.32.8 would require\n   \u2514\u2500 pythia8 >=8.312,<8.400.0a0, which cannot be installed because there are no viable options:\n      \u251C\u2500 pythia8 8.312 | 8.312 | 8.312 would require\n      \u2502  \u2514\u2500 _x86_64-microarch-level >=3, which cannot be installed because there are no viable options:\n      \u2502     \u2514\u2500 _x86_64-microarch-level 3 | 3 | 3 | 3 | 3 | 3 | 3 | 3 | 3 | 3 | 3 | 3 | 3 | 3 | 3 | 3 | 3 | 3 | 3 | 3 | 3 | 3 | 3 | 3 | 3 | 3 | 3 | 3 | 3 | 3 | 4 | 4 | 4 | 4 | 4 | 4 | 4 | 4 | 4 | 4 | 4 | 4 | 4 | 4 | 4 | 4 | 4 | 4 would require\n      \u2502        \u2514\u2500 __archspec ==1 cannonlake, for which no candidates were found.\n      \u251C\u2500 pythia8 8.312 | 8.312 | 8.312 would require\n      \u2502  \u2514\u2500 _x86_64-microarch-level >=1, which cannot be installed because there are no viable options:\n      \u2502     \u2514\u2500 _x86_64-microarch-level 1 | 1 | 1 | 1 | 1 | 1 | 1 | 1 | 1 | 1 | 1 | 1 | 2 | 2 | 2 | 2 | 2 | 2 | 2 | 2 | 2 | 2 | 2 | 2 | 2 | 2 | 2 | 2 | 2 | 2 | 2 | 2 | 2 | 2 | 2 | 2 would require\n      \u2502        \u2514\u2500 __archspec ==1 core2, for which no candidates were found.\n      \u2514\u2500 pythia8 8.312 | 8.312 | 8.312 | 8.312 | 8.312 | 8.312 | 8.312 | 8.312 | 8.312 | 8.312 | 8.312 | 8.312 | 8.312 | 8.312 | 8.312 | 8.312 | 8.312 | 8.312 | 8.312 | 8.312 | 8.312 | 8.312 | 8.312 | 8.312 would require\n         \u2514\u2500 python >=3.10,<3.11.0a0, for which no candidates were found.\n\n        </pre>\n        </div>\n        </details>"
    }
  },
  "awaiting-parents": [
    "omicron",
    "vetoperf",
    "upv",
    "gds-monitor-apps"
  ],
  "awaiting-pr": [],
  "bot-error": [],
  "done": [
    "gds-root-extensions"
  ],
  "in-pr": [
    "stir",
    "gds-gui",
    "delphes",
    "cwb"
  ],
  "not-solvable": [
    "yoda",
    "rapidsim",
    "ostaphep",
    "lhcb-simpletools",
    "hammer",
    "gwollum",
    "cds-crtools",
    "gds-dmt"
  ]
}