{
 "base": {
  "repo": {
   "name": "awscli2-feedstock"
  }
 },
 "closed_at": null,
 "created_at": "2025-02-07T22:14:38Z",
 "draft": false,
 "e_tag": "\"d40d6f7a57507e84c254e8da21237ea53c9cfec2d67fd48e22b6237e1867cb81\"",
 "head": {
  "ref": "2.24.0_hdc30cc"
 },
 "html_url": "https://github.com/conda-forge/awscli2-feedstock/pull/284",
 "id": 2323213673,
 "labels": [],
 "last_modified": null,
 "mergeable": null,
 "mergeable_state": "unknown",
 "merged": false,
 "merged_at": null,
 "number": 284,
 "state": "open",
 "updated_at": "2025-02-07T22:14:38Z"
}