{
 "base": {
  "repo": {
   "name": "meteofetch-feedstock"
  }
 },
 "closed_at": null,
 "created_at": "2025-02-04T11:51:09Z",
 "draft": false,
 "e_tag": "\"66b5ba9863ff60ae46086dfb231780f684c8f3cd43d617f97910ac683e2a04be\"",
 "head": {
  "ref": "0.2.5_hde1121"
 },
 "html_url": "https://github.com/conda-forge/meteofetch-feedstock/pull/1",
 "id": 2314957423,
 "labels": [],
 "last_modified": null,
 "mergeable": null,
 "mergeable_state": "unknown",
 "merged": false,
 "merged_at": null,
 "number": 1,
 "state": "open",
 "updated_at": "2025-02-04T11:51:09Z"
}