{
 "ETag": "W/\"fac6487ce0970d04adfc8ff39cf5419d70c5d95ce7ef71c3c63eaa175bc02553\"",
 "Last-Modified": "Fri, 24 Jan 2025 17:53:36 GMT",
 "base": {
  "repo": {
   "name": "r-rworkflows-feedstock"
  }
 },
 "closed_at": null,
 "created_at": "2025-01-24T17:51:54Z",
 "draft": false,
 "e_tag": "\"b1f5e2e52765894d5c451db8f2cbab9d40e5870fb10428ad02327b37a2982def\"",
 "head": {
  "ref": "1.0.6_he859b6"
 },
 "html_url": "https://github.com/conda-forge/r-rworkflows-feedstock/pull/3",
 "id": 2297308793,
 "labels": [],
 "last_modified": null,
 "mergeable": true,
 "mergeable_state": "clean",
 "merged": false,
 "merged_at": null,
 "number": 3,
 "state": "open",
 "updated_at": "2025-01-24T17:53:36Z"
}