{
 "ETag": "W/\"78f643a64007ec4ee0e48ddba55c5dea3016087288605343e81161ff368e4158\"",
 "Last-Modified": "Mon, 10 Feb 2025 19:25:02 GMT",
 "base": {
  "repo": {
   "name": "xlwings-feedstock"
  }
 },
 "closed_at": null,
 "created_at": "2025-02-10T19:23:35Z",
 "draft": false,
 "e_tag": "\"6eb48b68dff2da6f4d5f8cb831c4f6c6988caa7790721e89be1ecba54a4f1786\"",
 "head": {
  "ref": "0.33.7_hcf3b4d"
 },
 "html_url": "https://github.com/conda-forge/xlwings-feedstock/pull/168",
 "id": 2326954807,
 "labels": [],
 "last_modified": null,
 "mergeable": true,
 "mergeable_state": "clean",
 "merged": false,
 "merged_at": null,
 "number": 168,
 "state": "open",
 "updated_at": "2025-02-10T19:25:02Z"
}