{
 "ETag": "W/\"ebc82f1bc3a1ab8a479169dca2627c75c6ecfa86738591d1eec27c57b426575b\"",
 "Last-Modified": "Fri, 14 Feb 2025 08:59:19 GMT",
 "base": {
  "repo": {
   "name": "moscot-feedstock"
  }
 },
 "closed_at": null,
 "created_at": "2025-02-14T08:57:53Z",
 "draft": false,
 "e_tag": "\"d9b3510e09f040eb24a326f0a4c96617ebe6232b1aefb352c0dee3159e1f7b86\"",
 "head": {
  "ref": "0.4.1_h8ecd56"
 },
 "html_url": "https://github.com/conda-forge/moscot-feedstock/pull/16",
 "id": 2335570327,
 "labels": [],
 "last_modified": null,
 "mergeable": true,
 "mergeable_state": "clean",
 "merged": false,
 "merged_at": null,
 "number": 16,
 "state": "open",
 "updated_at": "2025-02-14T08:59:19Z"
}