{
 "base": {
  "repo": {
   "name": "mccode-antlr-feedstock"
  }
 },
 "closed_at": null,
 "created_at": "2025-02-19T05:47:03Z",
 "draft": false,
 "e_tag": "\"20e6a59bcfe10b6ae18dd856bbcea3a37ae9d8ee6d26320f25df32c9031f49bc\"",
 "head": {
  "ref": "0.10.1_h56d930"
 },
 "html_url": "https://github.com/conda-forge/mccode-antlr-feedstock/pull/7",
 "id": 2343697081,
 "labels": [],
 "last_modified": null,
 "mergeable": null,
 "mergeable_state": "unknown",
 "merged": false,
 "merged_at": null,
 "number": 7,
 "state": "open",
 "updated_at": "2025-02-19T05:47:03Z"
}