{
 "base": {
  "repo": {
   "name": "virtualenv-feedstock"
  }
 },
 "closed_at": null,
 "created_at": "2025-02-11T08:10:53Z",
 "draft": false,
 "e_tag": "\"2946359bbe0d53930e8eb7b93b723854fa77622c8288f44831f98c51d3b7d860\"",
 "head": {
  "ref": "20.29.2_h33b85d"
 },
 "html_url": "https://github.com/conda-forge/virtualenv-feedstock/pull/138",
 "id": 2328008919,
 "labels": [],
 "last_modified": null,
 "mergeable": null,
 "mergeable_state": "unknown",
 "merged": false,
 "merged_at": null,
 "number": 138,
 "state": "open",
 "updated_at": "2025-02-11T08:10:53Z"
}