{
 "base": {
  "repo": {
   "name": "openinference-instrumentation-vertexai-feedstock"
  }
 },
 "closed_at": null,
 "created_at": "2025-02-18T21:18:25Z",
 "draft": false,
 "e_tag": "\"1bf8ac60beb92e8601f322570dbb07be20c1d8edd36018eb293b42b83f430763\"",
 "head": {
  "ref": "0.1.7_h4c7f2d"
 },
 "html_url": "https://github.com/conda-forge/openinference-instrumentation-vertexai-feedstock/pull/8",
 "id": 2343146377,
 "labels": [],
 "last_modified": null,
 "mergeable": null,
 "mergeable_state": "unknown",
 "merged": false,
 "merged_at": null,
 "number": 8,
 "state": "open",
 "updated_at": "2025-02-18T21:18:25Z"
}