{
 "ETag": "W/\"a4c16d4de12ad1144423043925f21df033af9ff9d55c2e164d9f05409e1058bd\"",
 "Last-Modified": "Thu, 30 Jan 2025 21:07:54 GMT",
 "base": {
  "repo": {
   "name": "shinywidgets-feedstock"
  }
 },
 "closed_at": "2025-01-30T21:07:49Z",
 "created_at": "2025-01-30T21:03:03Z",
 "draft": false,
 "e_tag": "\"40b0a7aa28dd0762702755ef719c5e6cad79edba018fe0483fcaa3c2c14dfea2\"",
 "head": {
  "ref": "this_is_not_a_branch"
 },
 "html_url": "https://github.com/conda-forge/shinywidgets-feedstock/pull/9",
 "id": 2307743370,
 "labels": [],
 "last_modified": null,
 "mergeable": null,
 "mergeable_state": "unknown",
 "merged": true,
 "merged_at": "2025-01-30T21:07:49Z",
 "number": 9,
 "state": "closed",
 "updated_at": "2025-01-30T21:07:54Z"
}