{
 "base": {
  "repo": {
   "name": "mlx-vlm-feedstock"
  }
 },
 "closed_at": null,
 "created_at": "2025-01-30T05:58:11Z",
 "draft": false,
 "e_tag": "\"7657bf40905baa1257e85dafc415cc71808d7eb850ffc2e31938938ab50ac064\"",
 "head": {
  "ref": "0.1.12_h275f0e"
 },
 "html_url": "https://github.com/conda-forge/mlx-vlm-feedstock/pull/26",
 "id": 2306104276,
 "labels": [],
 "last_modified": null,
 "mergeable": null,
 "mergeable_state": "unknown",
 "merged": false,
 "merged_at": null,
 "number": 26,
 "state": "open",
 "updated_at": "2025-01-30T05:58:11Z"
}