{
 "base": {
  "repo": {
   "name": "boto3-feedstock"
  }
 },
 "closed_at": null,
 "created_at": "2025-01-30T01:56:21Z",
 "draft": false,
 "e_tag": "\"57876bfdb56271ef1c0b2a10916036d9d0a804cd029ce16dab69a5ce1e8e7820\"",
 "head": {
  "ref": "1.36.9_h4b141a"
 },
 "html_url": "https://github.com/conda-forge/boto3-feedstock/pull/1701",
 "id": 2305888287,
 "labels": [],
 "last_modified": null,
 "mergeable": null,
 "mergeable_state": "unknown",
 "merged": false,
 "merged_at": null,
 "number": 1701,
 "state": "open",
 "updated_at": "2025-01-30T01:56:21Z"
}