{
 "ETag": "W/\"ec425a03318d6266645436d39cb43af3b1ad88be54844bef89f37a6aa469b830\"",
 "Last-Modified": "Sun, 09 Feb 2025 11:39:34 GMT",
 "base": {
  "repo": {
   "name": "tensorflow-feedstock"
  }
 },
 "closed_at": "2025-02-09T11:39:34Z",
 "created_at": "2025-01-11T13:03:13Z",
 "draft": false,
 "e_tag": "\"acfbb5c81d124d72848db423a137eff7be7da048954ae677ab8bb03cdfba6160\"",
 "head": {
  "ref": "rebuild-flatbuffers241223-0-1_h6cdbab"
 },
 "html_url": "https://github.com/conda-forge/tensorflow-feedstock/pull/413",
 "id": 2272026386,
 "labels": [],
 "last_modified": null,
 "mergeable": false,
 "mergeable_state": "dirty",
 "merged": false,
 "merged_at": null,
 "number": 413,
 "state": "closed",
 "updated_at": "2025-02-09T11:39:34Z"
}